{
    "INFO": {
        "NAME": "Dongnae_300_1_00065",
        "DATA_CREATED": "2023-10-19",
        "DESCRIPTION": "없음",
        "URL": "https://safecity.busan.go.kr",
        "1HR_RAINFALL": 136.64,
        "RAINFALLOBSERVATION_POSITION": "부산",
        "RIVEROBSERVATION_POSITION": "없음",
        "BRIDGE_NAME": "없음",
        "TIDEOBSERVATION_POSITION": "없음",
        "OBSERVATIONAL_TIDE": 0,
        "24HR_RAINFALL": 136.64
    },
    "CATEGORIES": {
        "ID": "Dongnae_300_1_00065",
        "NAME": "Dongnae_300_1",
        "CATEGORY": 1
    },
    "IMAGE": {
        "ID": "Dongnae_300_1_00065",
        "WIDTH": "2400",
        "HEIGHT": "1600",
        "FILE_NAME": "Dongnae_300_1_00065"
    },
    "ANNOTATIONS": [
        {
            "ID": "6",
            "IMAGE_ID": "Dongnae_300_1_00065",
            "CATEGORY_ID": "Dongnae_300_1_00065",
            "SEGMENTATION": "폴리곤",
            "COORDINATE": [
                [
                    1951.759719999507,
                    1408.788320000283
                ],
                [
                    1831.791439999826,
                    1410.598799999803
                ],
                [
                    1893.890719999559,
                    1127.877280000597
                ],
                [
                    2071.727959999815,
                    1406.977839999832
                ],
                [
                    1951.759719999507,
                    1408.788320000283
                ]
            ]
        },
        {
            "ID": "6",
            "IMAGE_ID": "Dongnae_300_1_00065",
            "CATEGORY_ID": "Dongnae_300_1_00065",
            "SEGMENTATION": "폴리곤",
            "COORDINATE": [
                [
                    2304.422519999556,
                    923.4836800005287
                ],
                [
                    2400.0,
                    922.041240000166
                ],
                [
                    2400.0,
                    1042.03684000019
                ],
                [
                    2306.233039999381,
                    1043.45196000021
                ],
                [
                    2304.422519999556,
                    923.4836800005287
                ]
            ]
        },
        {
            "ID": "6",
            "IMAGE_ID": "Dongnae_300_1_00065",
            "CATEGORY_ID": "Dongnae_300_1_00065",
            "SEGMENTATION": "폴리곤",
            "COORDINATE": [
                [
                    1670.44927999936,
                    931.5335200000554
                ],
                [
                    1706.391719999723,
                    1052.504560000263
                ],
                [
                    1559.502039999701,
                    1013.643199999817
                ],
                [
                    1630.066199999303,
                    940.9190400000662
                ],
                [
                    1663.117279999889,
                    906.8563200002536
                ],
                [
                    1670.44927999936,
                    931.5335200000554
                ]
            ]
        },
        {
            "ID": "6",
            "IMAGE_ID": "Dongnae_300_1_00065",
            "CATEGORY_ID": "Dongnae_300_1_00065",
            "SEGMENTATION": "폴리곤",
            "COORDINATE": [
                [
                    2304.422519999556,
                    923.4836800005287
                ],
                [
                    2027.799680000171,
                    879.0209600003436
                ],
                [
                    2193.448199999519,
                    794.3667999999598
                ],
                [
                    2234.753560000099,
                    773.257840000093
                ],
                [
                    2236.936999999918,
                    772.1419999999925
                ],
                [
                    2304.422519999556,
                    923.4836800005287
                ]
            ]
        },
        {
            "ID": "6",
            "IMAGE_ID": "Dongnae_300_1_00065",
            "CATEGORY_ID": "Dongnae_300_1_00065",
            "SEGMENTATION": "폴리곤",
            "COORDINATE": [
                [
                    2400.0,
                    300.836959999986
                ],
                [
                    2400.0,
                    603.1550000002608
                ],
                [
                    2352.58844000008,
                    575.330880000256
                ],
                [
                    2321.749880000018,
                    557.2328400006518
                ],
                [
                    2301.708159999922,
                    545.4710800005123
                ],
                [
                    2153.314319999889,
                    458.3840399999171
                ],
                [
                    2119.3981599994,
                    438.4798800004646
                ],
                [
                    2145.234639999457,
                    425.8063599998131
                ],
                [
                    2254.461360000074,
                    372.227640000172
                ],
                [
                    2271.07620000001,
                    364.0776399997994
                ],
                [
                    2294.080679999664,
                    352.7932799998671
                ],
                [
                    2400.0,
                    300.836959999986
                ]
            ]
        },
        {
            "ID": "6",
            "IMAGE_ID": "Dongnae_300_1_00065",
            "CATEGORY_ID": "Dongnae_300_1_00065",
            "SEGMENTATION": "폴리곤",
            "COORDINATE": [
                [
                    2400.0,
                    0.0
                ],
                [
                    2400.0,
                    91.89783999975771
                ],
                [
                    2398.117359999567,
                    90.72200000006706
                ],
                [
                    2252.862479999661,
                    0.0
                ],
                [
                    2400.0,
                    0.0
                ]
            ]
        },
        {
            "ID": "7",
            "IMAGE_ID": "Dongnae_300_1_00065",
            "CATEGORY_ID": "Dongnae_300_1_00065",
            "SEGMENTATION": "폴리곤",
            "COORDINATE": [
                [
                    1953.570199999958,
                    1528.756560000591
                ],
                [
                    1951.759719999507,
                    1408.788320000283
                ],
                [
                    2071.727959999815,
                    1406.977839999832
                ],
                [
                    2073.538439999335,
                    1526.94608000014
                ],
                [
                    1953.570199999958,
                    1528.756560000591
                ]
            ]
        },
        {
            "ID": "8",
            "IMAGE_ID": "Dongnae_300_1_00065",
            "CATEGORY_ID": "Dongnae_300_1_00065",
            "SEGMENTATION": "폴리곤",
            "COORDINATE": [
                [
                    2297.626879999414,
                    1600.0
                ],
                [
                    2212.145399999805,
                    1600.0
                ],
                [
                    2252.982520000078,
                    1490.546040000394
                ],
                [
                    2297.626879999414,
                    1600.0
                ]
            ]
        },
        {
            "ID": "8",
            "IMAGE_ID": "Dongnae_300_1_00065",
            "CATEGORY_ID": "Dongnae_300_1_00065",
            "SEGMENTATION": "폴리곤",
            "COORDINATE": [
                [
                    1953.570199999958,
                    1528.756560000591
                ],
                [
                    1833.601919999346,
                    1530.567040000111
                ],
                [
                    1831.791439999826,
                    1410.598799999803
                ],
                [
                    1951.759719999507,
                    1408.788320000283
                ],
                [
                    1953.570199999958,
                    1528.756560000591
                ]
            ]
        },
        {
            "ID": "8",
            "IMAGE_ID": "Dongnae_300_1_00065",
            "CATEGORY_ID": "Dongnae_300_1_00065",
            "SEGMENTATION": "폴리곤",
            "COORDINATE": [
                [
                    2332.586360000074,
                    1163.049879999831
                ],
                [
                    2308.043560000136,
                    1163.42023999989
                ],
                [
                    2306.511880000122,
                    1061.930080000311
                ],
                [
                    2306.233039999381,
                    1043.45196000021
                ],
                [
                    2400.0,
                    1042.03684000019
                ],
                [
                    2400.0,
                    1162.032480000518
                ],
                [
                    2332.586360000074,
                    1163.049879999831
                ]
            ]
        },
        {
            "ID": "5",
            "IMAGE_ID": "Dongnae_300_1_00065",
            "CATEGORY_ID": "Dongnae_300_1_00065",
            "SEGMENTATION": "폴리곤",
            "COORDINATE": [
                [
                    2400.0,
                    1162.032480000518
                ],
                [
                    2400.0,
                    1600.0
                ],
                [
                    2297.626879999414,
                    1600.0
                ],
                [
                    2252.982520000078,
                    1490.546040000394
                ],
                [
                    2212.145399999805,
                    1600.0
                ],
                [
                    2033.59683999978,
                    1600.0
                ],
                [
                    2063.854720000178,
                    1584.161319999956
                ],
                [
                    2098.949120000005,
                    1565.013319999911
                ],
                [
                    2149.285120000131,
                    1533.910120000131
                ],
                [
                    2183.515519999899,
                    1506.61091999989
                ],
                [
                    2248.7795199994,
                    1443.687719999813
                ],
                [
                    2306.070720000193,
                    1379.878120000474
                ],
                [
                    2296.509920000099,
                    1333.967720000073
                ],
                [
                    2294.131519999355,
                    1334.875719999894
                ],
                [
                    2304.216319999658,
                    1379.453320000321
                ],
                [
                    2294.988319999538,
                    1381.833320000209
                ],
                [
                    2259.696320000105,
                    1248.938920000568
                ],
                [
                    2348.479519999586,
                    1226.587720000185
                ],
                [
                    2336.475519999862,
                    1178.602119999938
                ],
                [
                    2332.586360000074,
                    1163.049879999831
                ],
                [
                    2400.0,
                    1162.032480000518
                ]
            ]
        },
        {
            "ID": "5",
            "IMAGE_ID": "Dongnae_300_1_00065",
            "CATEGORY_ID": "Dongnae_300_1_00065",
            "SEGMENTATION": "폴리곤",
            "COORDINATE": [
                [
                    2400.0,
                    762.8076400002465
                ],
                [
                    2400.0,
                    847.0820000004023
                ],
                [
                    2340.461919999681,
                    627.1981199998409
                ],
                [
                    2328.592319999821,
                    582.8109200000763
                ],
                [
                    2324.744319999591,
                    568.4301200006157
                ],
                [
                    2321.749880000018,
                    557.2328400006518
                ],
                [
                    2352.58844000008,
                    575.330880000256
                ],
                [
                    2349.583519999869,
                    576.1629200000316
                ],
                [
                    2361.698719999753,
                    621.4781200001016
                ],
                [
                    2400.0,
                    762.8076400002465
                ]
            ]
        },
        {
            "ID": "5",
            "IMAGE_ID": "Dongnae_300_1_00065",
            "CATEGORY_ID": "Dongnae_300_1_00065",
            "SEGMENTATION": "폴리곤",
            "COORDINATE": [
                [
                    2304.422519999556,
                    923.4836800005287
                ],
                [
                    2236.936999999918,
                    772.1419999999925
                ],
                [
                    2234.753560000099,
                    773.257840000093
                ],
                [
                    2234.567520000041,
                    771.1789199998602
                ],
                [
                    2203.773919999599,
                    661.8437200002372
                ],
                [
                    2157.022719999775,
                    473.3365200003609
                ],
                [
                    2153.314319999889,
                    458.3840399999171
                ],
                [
                    2301.708159999922,
                    545.4710800005123
                ],
                [
                    2313.706720000133,
                    589.0197200002149
                ],
                [
                    2355.893120000139,
                    762.3725200006738
                ],
                [
                    2369.400320000015,
                    812.6549200005829
                ],
                [
                    2393.273120000027,
                    890.7477200003341
                ],
                [
                    2394.373920000158,
                    897.1589200003073
                ],
                [
                    2400.0,
                    918.2774000000209
                ],
                [
                    2400.0,
                    922.041240000166
                ],
                [
                    2304.422519999556,
                    923.4836800005287
                ]
            ]
        },
        {
            "ID": "5",
            "IMAGE_ID": "Dongnae_300_1_00065",
            "CATEGORY_ID": "Dongnae_300_1_00065",
            "SEGMENTATION": "폴리곤",
            "COORDINATE": [
                [
                    2304.422519999556,
                    923.4836800005287
                ],
                [
                    2306.233039999381,
                    1043.45196000021
                ],
                [
                    2306.511880000122,
                    1061.930080000311
                ],
                [
                    2285.513119999319,
                    981.3989200005308
                ],
                [
                    2228.11391999945,
                    946.0021200003102
                ],
                [
                    2184.009920000099,
                    957.81172000058
                ],
                [
                    2021.872320000082,
                    1001.621319999918
                ],
                [
                    2014.413119999692,
                    969.8429200006649
                ],
                [
                    1987.86352000013,
                    981.3549199998379
                ],
                [
                    1762.160319999792,
                    1039.938920000568
                ],
                [
                    1684.984319999814,
                    1060.882919999771
                ],
                [
                    1644.255520000122,
                    1070.889320000075
                ],
                [
                    1619.553119999357,
                    1076.958120000549
                ],
                [
                    1583.379519999959,
                    1085.591719999909
                ],
                [
                    1547.661919999868,
                    1094.118119999766
                ],
                [
                    1469.165919999592,
                    1115.362120000646
                ],
                [
                    1443.061919999309,
                    1122.67572000064
                ],
                [
                    1299.313120000064,
                    1158.904520000331
                ],
                [
                    1266.845919999294,
                    1168.182120000012
                ],
                [
                    1222.709919999354,
                    1180.791720000096
                ],
                [
                    1176.785919999704,
                    1193.915719999932
                ],
                [
                    1206.093919999897,
                    1314.021320000291
                ],
                [
                    1185.689119999297,
                    1320.068520000204
                ],
                [
                    1162.071519999765,
                    1227.908520000055
                ],
                [
                    1117.769919999875,
                    1238.320520000532
                ],
                [
                    1108.359519999474,
                    1224.314919999801
                ],
                [
                    1025.692319999449,
                    1242.421320000663
                ],
                [
                    917.8739200001583,
                    1275.440520000644
                ],
                [
                    913.3107199994847,
                    1277.065320000052
                ],
                [
                    903.3595199994743,
                    1296.670119999908
                ],
                [
                    894.6195200001821,
                    1299.894120000303
                ],
                [
                    844.7787199998274,
                    1308.946120000444
                ],
                [
                    832.7507199998945,
                    1312.383720000274
                ],
                [
                    817.0459199994802,
                    1297.201319999993
                ],
                [
                    712.9091199999675,
                    1326.571720000356
                ],
                [
                    761.8755199993029,
                    1516.093319999985
                ],
                [
                    779.6427999995649,
                    1600.0
                ],
                [
                    626.4267600001767,
                    1600.0
                ],
                [
                    622.6139199994504,
                    1583.98852000013
                ],
                [
                    587.2075199997053,
                    1449.404520000331
                ],
                [
                    556.0579199995846,
                    1331.518920000643
                ],
                [
                    551.5283199995756,
                    1324.230920000002
                ],
                [
                    547.9091199999675,
                    1320.770120000467
                ],
                [
                    540.4667199999094,
                    1316.394919999875
                ],
                [
                    537.4035200001672,
                    1314.589320000261
                ],
                [
                    534.0771199995652,
                    1313.650120000355
                ],
                [
                    531.9155199993402,
                    1313.299720000476
                ],
                [
                    529.195519999601,
                    1313.293320000172
                ],
                [
                    522.8219200000167,
                    1314.201319999993
                ],
                [
                    420.7963199997321,
                    1342.166919999756
                ],
                [
                    392.8971199998632,
                    1320.442119999789
                ],
                [
                    507.1779199996963,
                    1287.334119999781
                ],
                [
                    510.0819199997932,
                    1285.522119999863
                ],
                [
                    513.3651200002059,
                    1282.60532000009
                ],
                [
                    515.3683199994266,
                    1280.418920000084
                ],
                [
                    517.9115199996158,
                    1275.340520000085
                ],
                [
                    519.1851199995726,
                    1270.437320000492
                ],
                [
                    519.1875200001523,
                    1267.898120000027
                ],
                [
                    517.9243199992925,
                    1263.721320000477
                ],
                [
                    503.5811199992895,
                    1233.54291999992
                ],
                [
                    494.4091199999675,
                    1217.041319999844
                ],
                [
                    482.6747199995443,
                    1195.918920000084
                ],
                [
                    473.9171199994162,
                    1180.164520000108
                ],
                [
                    455.9939199993387,
                    1140.724520000629
                ],
                [
                    445.0627199998125,
                    1106.554920000024
                ],
                [
                    434.004319999367,
                    1079.066120000556
                ],
                [
                    422.5547199994326,
                    1065.666919999756
                ],
                [
                    420.9547199998051,
                    1063.522920000367
                ],
                [
                    417.6027199998498,
                    1061.114920000546
                ],
                [
                    412.0299199996516,
                    1058.410120000131
                ],
                [
                    407.7915199995041,
                    1056.926920000464
                ],
                [
                    401.6283200001344,
                    1056.915719999932
                ],
                [
                    393.0587200000882,
                    1057.089320000261
                ],
                [
                    389.0747199999169,
                    1057.080520000309
                ],
                [
                    374.649120000191,
                    1059.61091999989
                ],
                [
                    186.9883199995384,
                    1108.35252000019
                ],
                [
                    63.75552000012249,
                    1145.106920000166
                ],
                [
                    0.0,
                    1162.401360000484
                ],
                [
                    0.0,
                    1121.616640000604
                ],
                [
                    61.40591999981552,
                    1105.764520000666
                ],
                [
                    162.3683199994266,
                    1078.03732000012
                ],
                [
                    384.8035199996084,
                    1025.066120000556
                ],
                [
                    362.1139199994504,
                    927.8405200000852
                ],
                [
                    344.6523199994117,
                    853.0109200002626
                ],
                [
                    304.4579199999571,
                    693.1325200004503
                ],
                [
                    247.0771199995652,
                    468.5341199999675
                ],
                [
                    229.1635199999437,
                    411.3997200001031
                ],
                [
                    201.2131199995056,
                    293.7501199999824
                ],
                [
                    157.015519999899,
                    123.6069200001657
                ],
                [
                    126.5775600001216,
                    0.0
                ],
                [
                    253.408239999786,
                    0.0
                ],
                [
                    263.7043199995533,
                    41.58372000046074
                ],
                [
                    288.6635199999437,
                    139.3397200005129
                ],
                [
                    325.9435200002044,
                    290.1877199998125
                ],
                [
                    391.189119999297,
                    543.5693199997768
                ],
                [
                    406.9019200000912,
                    591.4013200001791
                ],
                [
                    427.353919999674,
                    679.465320000425
                ],
                [
                    444.1699199993163,
                    748.1413200004026
                ],
                [
                    448.5475199995562,
                    750.8797200005502
                ],
                [
                    455.665919999592,
                    751.0749200005084
                ],
                [
                    458.7563199996948,
                    750.7133200000972
                ],
                [
                    460.7531199995428,
                    749.983719999902
                ],
                [
                    502.7843199996278,
                    672.9277200000361
                ],
                [
                    633.8019199995324,
                    451.8061199998483
                ],
                [
                    709.7587199993432,
                    325.8453200003132
                ],
                [
                    709.2131199995056,
                    323.6413200004026
                ],
                [
                    708.490720000118,
                    322.7245200006291
                ],
                [
                    705.9347199993208,
                    322.7189199998975
                ],
                [
                    704.1139199994504,
                    322.9029200002551
                ],
                [
                    687.7707199994475,
                    341.2277199998498
                ],
                [
                    549.9451199993491,
                    487.0661200005561
                ],
                [
                    522.7627199999988,
                    518.3725200006738
                ],
                [
                    486.3451199997216,
                    555.4565200004727
                ],
                [
                    440.1547199999914,
                    578.5517199998721
                ],
                [
                    442.6123199993744,
                    595.8949199998751
                ],
                [
                    422.0315199997276,
                    601.929320000112
                ],
                [
                    418.7507199998945,
                    586.7197200004011
                ],
                [
                    412.0683199996129,
                    542.2861200002953
                ],
                [
                    398.2307199994102,
                    481.7165200002491
                ],
                [
                    412.5051199998707,
                    477.7133200000972
                ],
                [
                    457.5675200000405,
                    459.1341200005263
                ],
                [
                    477.7643200000748,
                    470.9245199998841
                ],
                [
                    482.9075199998915,
                    472.2197200004011
                ],
                [
                    486.3723200000823,
                    472.7669200003147
                ],
                [
                    488.1811199998483,
                    472.0517199998721
                ],
                [
                    490.5339199993759,
                    470.2485199999064
                ],
                [
                    529.5427199993283,
                    437.0373200001195
                ],
                [
                    580.2163199996576,
                    382.1381200002506
                ],
                [
                    677.5395200001076,
                    271.5253200000152
                ],
                [
                    695.0403199996799,
                    253.3381200004369
                ],
                [
                    696.8547200001776,
                    250.0829199999571
                ],
                [
                    698.6963200001046,
                    245.9029200002551
                ],
                [
                    698.8835199996829,
                    244.272520000115
                ],
                [
                    638.0349599998444,
                    0.0
                ],
                [
                    751.106279999949,
                    0.0
                ],
                [
                    793.667519999668,
                    176.7005200004205
                ],
                [
                    799.7067200001329,
                    201.7685200003907
                ],
                [
                    807.169119999744,
                    232.7469199998304
                ],
                [
                    815.2683199997991,
                    266.3781200004742
                ],
                [
                    837.2595199998468,
                    303.1861200006679
                ],
                [
                    921.9915199996904,
                    360.6685199998319
                ],
                [
                    946.5675200000405,
                    376.8573200004175
                ],
                [
                    1024.488319999538,
                    427.2421200005338
                ],
                [
                    1078.509920000099,
                    453.6829200005159
                ],
                [
                    1098.039520000108,
                    463.6397200003266
                ],
                [
                    1100.736320000142,
                    464.0029199998826
                ],
                [
                    1104.906719999388,
                    463.6485200002789
                ],
                [
                    1111.060320000164,
                    462.935720000416
                ],
                [
                    1178.054719999433,
                    446.0645200004801
                ],
                [
                    1250.289919999428,
                    427.8749200003222
                ],
                [
                    1281.841119999997,
                    418.3517200006172
                ],
                [
                    1397.261919999495,
                    386.6501200003549
                ],
                [
                    1423.221119999886,
                    379.5229200003669
                ],
                [
                    1425.425919999368,
                    378.2421200005338
                ],
                [
                    1454.642719999887,
                    334.6501200003549
                ],
                [
                    1491.333920000121,
                    272.6229199999943
                ],
                [
                    1511.221919999458,
                    232.1357200006023
                ],
                [
                    1590.533919999376,
                    101.7125200005248
                ],
                [
                    1591.265920000151,
                    98.25332000013441
                ],
                [
                    1585.502719999291,
                    60.65732000023127
                ],
                [
                    1567.559159999713,
                    0.0
                ],
                [
                    1648.334759999998,
                    0.0
                ],
                [
                    1660.395519999787,
                    44.69892000034451
                ],
                [
                    1678.465119999833,
                    111.6605200003833
                ],
                [
                    1734.290719999932,
                    138.3813200006261
                ],
                [
                    1790.128320000134,
                    152.4381200000644
                ],
                [
                    1828.459520000033,
                    169.9421199997887
                ],
                [
                    1866.037119999528,
                    185.778920000419
                ],
                [
                    1874.093919999897,
                    185.7933200001717
                ],
                [
                    1881.018720000051,
                    184.3485200004652
                ],
                [
                    1946.751519999467,
                    167.5893200002611
                ],
                [
                    2023.265119999647,
                    147.7629200005904
                ],
                [
                    2027.041919999756,
                    145.965320000425
                ],
                [
                    2032.538719999604,
                    141.2197200004011
                ],
                [
                    2036.900320000015,
                    137.9501200001687
                ],
                [
                    2053.293920000084,
                    114.2189199998975
                ],
                [
                    2056.406719999388,
                    105.272520000115
                ],
                [
                    2056.41232000012,
                    102.7365199998021
                ],
                [
                    2055.868319999427,
                    96.90932000055909
                ],
                [
                    2043.042719999328,
                    41.623720000498
                ],
                [
                    2031.618999999948,
                    0.0
                ],
                [
                    2155.190479999408,
                    0.0
                ],
                [
                    2162.767519999295,
                    25.74531999975443
                ],
                [
                    2183.056319999509,
                    102.7253200002015
                ],
                [
                    2192.307519999333,
                    137.8245200002566
                ],
                [
                    2196.859120000154,
                    139.4013200001791
                ],
                [
                    2198.765920000151,
                    139.7245200006291
                ],
                [
                    2201.302319999784,
                    139.5537200002
                ],
                [
                    2204.761520000175,
                    138.8861199999228
                ],
                [
                    2207.476719999686,
                    137.0049200002104
                ],
                [
                    2209.54871999938,
                    134.6069200001657
                ],
                [
                    2210.487519999966,
                    133.5197200002149
                ],
                [
                    2174.669400000013,
                    0.0
                ],
                [
                    2198.784679999575,
                    0.0
                ],
                [
                    2232.881519999355,
                    125.1913200002164
                ],
                [
                    2244.535120000131,
                    132.1481200000271
                ],
                [
                    2398.117359999567,
                    90.72200000006706
                ],
                [
                    2400.0,
                    91.89783999975771
                ],
                [
                    2400.0,
                    129.397520000115
                ],
                [
                    2256.257919999771,
                    166.204119999893
                ],
                [
                    2248.659119999968,
                    179.8489199997857
                ],
                [
                    2294.080679999664,
                    352.7932799998671
                ],
                [
                    2271.07620000001,
                    364.0776399997994
                ],
                [
                    2258.280319999903,
                    316.5781200006604
                ],
                [
                    2223.144719999284,
                    184.0261200005189
                ],
                [
                    2222.623119999655,
                    183.5425200005993
                ],
                [
                    2221.089920000173,
                    182.1213199999183
                ],
                [
                    2217.081519999541,
                    181.5253200000152
                ],
                [
                    2213.767519999295,
                    182.0453200004995
                ],
                [
                    2210.999119999819,
                    183.4873200003058
                ],
                [
                    2208.530720000155,
                    185.6589200003073
                ],
                [
                    2205.965919999406,
                    189.6425200002268
                ],
                [
                    2207.553519999608,
                    195.6669199997559
                ],
                [
                    2218.406719999388,
                    236.8429200006649
                ],
                [
                    2254.461360000074,
                    372.227640000172
                ],
                [
                    2145.234639999457,
                    425.8063599998131
                ],
                [
                    2139.253119999543,
                    401.6877199998125
                ],
                [
                    2102.536319999956,
                    268.9261199999601
                ],
                [
                    2097.852319999598,
                    259.1693200003356
                ],
                [
                    2083.800319999456,
                    246.1613199999556
                ],
                [
                    2071.033119999804,
                    239.5509200002998
                ],
                [
                    2067.221119999886,
                    239.5445199999958
                ],
                [
                    2061.183519999497,
                    239.1669199997559
                ],
                [
                    2057.359519999474,
                    239.1645200001076
                ],
                [
                    2047.103519999422,
                    240.9797200001776
                ],
                [
                    1937.797119999304,
                    271.0365200005472
                ],
                [
                    1897.753920000046,
                    281.0645200004801
                ],
                [
                    1856.411519999616,
                    280.808520000428
                ],
                [
                    1816.074719999917,
                    272.9461200004444
                ],
                [
                    1769.961919999681,
                    252.3781200004742
                ],
                [
                    1717.124319999479,
                    220.3573200004175
                ],
                [
                    1650.524319999851,
                    228.1261200001463
                ],
                [
                    1648.710719999857,
                    227.7533200001344
                ],
                [
                    1647.79311999958,
                    228.1181199997663
                ],
                [
                    1612.976319999434,
                    274.6749200001359
                ],
                [
                    1526.05391999986,
                    423.0053200004622
                ],
                [
                    1501.461120000109,
                    464.2589199999347
                ],
                [
                    1500.541919999756,
                    468.2365199998021
                ],
                [
                    1500.529919999652,
                    478.0517199998721
                ],
                [
                    1520.969920000061,
                    573.808520000428
                ],
                [
                    1556.599519999698,
                    708.3421200001612
                ],
                [
                    1600.201119999401,
                    869.1781200002879
                ],
                [
                    1622.057919999585,
                    939.7853199997917
                ],
                [
                    1623.706720000133,
                    940.8885200005025
                ],
                [
                    1624.433120000176,
                    941.0733200004324
                ],
                [
                    1626.060320000164,
                    941.2597200004384
                ],
                [
                    1630.066199999303,
                    940.9190400000662
                ],
                [
                    1559.502039999701,
                    1013.643199999817
                ],
                [
                    1706.391719999723,
                    1052.504560000263
                ],
                [
                    1670.44927999936,
                    931.5335200000554
                ],
                [
                    1794.681919999421,
                    902.5653200000525
                ],
                [
                    2072.882720000111,
                    823.7813200000674
                ],
                [
                    2193.448199999519,
                    794.3667999999598
                ],
                [
                    2027.799680000171,
                    879.0209600003436
                ],
                [
                    2304.422519999556,
                    923.4836800005287
                ],
                [
                    1188.699519999325,
                    1059.965320000425
                ],
                [
                    1156.952320000157,
                    929.4893200006336
                ],
                [
                    1228.250719999894,
                    805.0141200004146
                ],
                [
                    1183.538719999604,
                    635.5829199999571
                ],
                [
                    1091.043519999832,
                    581.609319999814
                ],
                [
                    1066.29311999958,
                    542.6149200005457
                ],
                [
                    853.3075199993327,
                    418.4549200003967
                ],
                [
                    852.0275200000033,
                    420.6541200000793
                ],
                [
                    846.7971199993044,
                    433.7125200005248
                ],
                [
                    707.2899199994281,
                    470.2533200001344
                ],
                [
                    611.169119999744,
                    637.9965200005099
                ],
                [
                    616.8499199999496,
                    639.6589200003073
                ],
                [
                    581.8123199995607,
                    700.4333199998364
                ],
                [
                    513.169119999744,
                    816.6213199999183
                ],
                [
                    498.9355199998245,
                    807.4885200001299
                ],
                [
                    467.4467199994251,
                    857.7253200002015
                ],
                [
                    465.979519999586,
                    861.7397199999541
                ],
                [
                    495.833920000121,
                    988.3725200006738
                ],
                [
                    500.2139200000092,
                    1006.946120000444
                ],
                [
                    504.4411199996248,
                    1021.765320000239
                ],
                [
                    522.6435199994594,
                    1085.596520000137
                ],
                [
                    525.0115200001746,
                    1091.435720000416
                ],
                [
                    578.8883199999109,
                    1108.76292000059
                ],
                [
                    628.4731200002134,
                    1022.349320000038
                ],
                [
                    653.6243199994788,
                    1036.677319999784
                ],
                [
                    603.5387199996039,
                    1131.546120000072
                ],
                [
                    608.2451200000942,
                    1160.930120000616
                ],
                [
                    656.5115200001746,
                    1187.440520000644
                ],
                [
                    696.982719999738,
                    1197.557320000604
                ],
                [
                    796.9755199998617,
                    1176.375719999894
                ],
                [
                    937.9683199999854,
                    1137.842120000161
                ],
                [
                    1125.833920000121,
                    1089.900520000607
                ],
                [
                    1149.936319999397,
                    1083.748519999906
                ],
                [
                    1180.593919999897,
                    1075.926920000464
                ],
                [
                    1188.699519999325,
                    1059.965320000425
                ],
                [
                    1238.561919999309,
                    1042.453320000321
                ],
                [
                    1262.881120000035,
                    1047.250119999982
                ],
                [
                    1291.619520000182,
                    1041.135720000602
                ],
                [
                    1523.654719999991,
                    980.6213199999183
                ],
                [
                    1543.04591999948,
                    961.0533199999481
                ],
                [
                    1531.809119999409,
                    915.9085200000554
                ],
                [
                    1483.677919999696,
                    727.4213200006634
                ],
                [
                    1461.249919999391,
                    648.8629200002179
                ],
                [
                    1424.920319999568,
                    506.3685200000182
                ],
                [
                    1422.570720000193,
                    499.0965200001374
                ],
                [
                    1412.877919999883,
                    488.4469200000167
                ],
                [
                    1335.185920000076,
                    506.8229200001806
                ],
                [
                    1237.217919999734,
                    533.300520000048
                ],
                [
                    1219.374719999731,
                    557.4893200006336
                ],
                [
                    1219.375519999303,
                    558.5805200003088
                ],
                [
                    1262.666720000096,
                    727.9965200005099
                ],
                [
                    1283.986719999462,
                    813.3437200002372
                ],
                [
                    1240.830719999969,
                    886.6733200000599
                ],
                [
                    1212.937919999473,
                    935.5837200004607
                ],
                [
                    1212.206720000133,
                    937.7421200005338
                ],
                [
                    1212.206720000133,
                    940.1069200001657
                ],
                [
                    1212.918719999492,
                    941.7445200001821
                ],
                [
                    1238.561919999309,
                    1042.453320000321
                ]
            ]
        },
        {
            "ID": "4",
            "IMAGE_ID": "Dongnae_300_1_00065",
            "CATEGORY_ID": "Dongnae_300_1_00065",
            "SEGMENTATION": "폴리곤",
            "COORDINATE": [
                [
                    407.7915199995041,
                    1056.926920000464
                ],
                [
                    412.0299199996516,
                    1058.410120000131
                ],
                [
                    417.6027199998498,
                    1061.114920000546
                ],
                [
                    420.9547199998051,
                    1063.522920000367
                ],
                [
                    422.5547199994326,
                    1065.666919999756
                ],
                [
                    434.004319999367,
                    1079.066120000556
                ],
                [
                    445.0627199998125,
                    1106.554920000024
                ],
                [
                    455.9939199993387,
                    1140.724520000629
                ],
                [
                    473.9171199994162,
                    1180.164520000108
                ],
                [
                    482.6747199995443,
                    1195.918920000084
                ],
                [
                    494.4091199999675,
                    1217.041319999844
                ],
                [
                    503.5811199992895,
                    1233.54291999992
                ],
                [
                    517.9243199992925,
                    1263.721320000477
                ],
                [
                    519.1875200001523,
                    1267.898120000027
                ],
                [
                    519.1851199995726,
                    1270.437320000492
                ],
                [
                    517.9115199996158,
                    1275.340520000085
                ],
                [
                    515.3683199994266,
                    1280.418920000084
                ],
                [
                    513.3651200002059,
                    1282.60532000009
                ],
                [
                    510.0819199997932,
                    1285.522119999863
                ],
                [
                    507.1779199996963,
                    1287.334119999781
                ],
                [
                    392.8971199998632,
                    1320.442119999789
                ],
                [
                    420.7963199997321,
                    1342.166919999756
                ],
                [
                    522.8219200000167,
                    1314.201319999993
                ],
                [
                    529.195519999601,
                    1313.293320000172
                ],
                [
                    531.9155199993402,
                    1313.299720000476
                ],
                [
                    534.0771199995652,
                    1313.650120000355
                ],
                [
                    537.4035200001672,
                    1314.589320000261
                ],
                [
                    540.4667199999094,
                    1316.394919999875
                ],
                [
                    547.9091199999675,
                    1320.770120000467
                ],
                [
                    551.5283199995756,
                    1324.230920000002
                ],
                [
                    556.0579199995846,
                    1331.518920000643
                ],
                [
                    587.2075199997053,
                    1449.404520000331
                ],
                [
                    622.6139199994504,
                    1583.98852000013
                ],
                [
                    626.4267600001767,
                    1600.0
                ],
                [
                    0.0,
                    1600.0
                ],
                [
                    0.0,
                    1162.401360000484
                ],
                [
                    63.75552000012249,
                    1145.106920000166
                ],
                [
                    186.9883199995384,
                    1108.35252000019
                ],
                [
                    374.649120000191,
                    1059.61091999989
                ],
                [
                    389.0747199999169,
                    1057.080520000309
                ],
                [
                    393.0587200000882,
                    1057.089320000261
                ],
                [
                    401.6283200001344,
                    1056.915719999932
                ],
                [
                    407.7915199995041,
                    1056.926920000464
                ]
            ]
        },
        {
            "ID": "4",
            "IMAGE_ID": "Dongnae_300_1_00065",
            "CATEGORY_ID": "Dongnae_300_1_00065",
            "SEGMENTATION": "폴리곤",
            "COORDINATE": [
                [
                    2285.513119999319,
                    981.3989200005308
                ],
                [
                    2306.511880000122,
                    1061.930080000311
                ],
                [
                    2308.043560000136,
                    1163.42023999989
                ],
                [
                    2332.586360000074,
                    1163.049879999831
                ],
                [
                    2336.475519999862,
                    1178.602119999938
                ],
                [
                    2348.479519999586,
                    1226.587720000185
                ],
                [
                    2259.696320000105,
                    1248.938920000568
                ],
                [
                    2294.988319999538,
                    1381.833320000209
                ],
                [
                    2304.216319999658,
                    1379.453320000321
                ],
                [
                    2294.131519999355,
                    1334.875719999894
                ],
                [
                    2296.509920000099,
                    1333.967720000073
                ],
                [
                    2306.070720000193,
                    1379.878120000474
                ],
                [
                    2248.7795199994,
                    1443.687719999813
                ],
                [
                    2183.515519999899,
                    1506.61091999989
                ],
                [
                    2149.285120000131,
                    1533.910120000131
                ],
                [
                    2098.949120000005,
                    1565.013319999911
                ],
                [
                    2063.854720000178,
                    1584.161319999956
                ],
                [
                    2033.59683999978,
                    1600.0
                ],
                [
                    779.6427999995649,
                    1600.0
                ],
                [
                    761.8755199993029,
                    1516.093319999985
                ],
                [
                    712.9091199999675,
                    1326.571720000356
                ],
                [
                    817.0459199994802,
                    1297.201319999993
                ],
                [
                    832.7507199998945,
                    1312.383720000274
                ],
                [
                    844.7787199998274,
                    1308.946120000444
                ],
                [
                    894.6195200001821,
                    1299.894120000303
                ],
                [
                    903.3595199994743,
                    1296.670119999908
                ],
                [
                    913.3107199994847,
                    1277.065320000052
                ],
                [
                    917.8739200001583,
                    1275.440520000644
                ],
                [
                    1025.692319999449,
                    1242.421320000663
                ],
                [
                    1108.359519999474,
                    1224.314919999801
                ],
                [
                    1117.769919999875,
                    1238.320520000532
                ],
                [
                    1162.071519999765,
                    1227.908520000055
                ],
                [
                    1185.689119999297,
                    1320.068520000204
                ],
                [
                    1206.093919999897,
                    1314.021320000291
                ],
                [
                    1176.785919999704,
                    1193.915719999932
                ],
                [
                    1222.709919999354,
                    1180.791720000096
                ],
                [
                    1266.845919999294,
                    1168.182120000012
                ],
                [
                    1299.313120000064,
                    1158.904520000331
                ],
                [
                    1443.061919999309,
                    1122.67572000064
                ],
                [
                    1469.165919999592,
                    1115.362120000646
                ],
                [
                    1547.661919999868,
                    1094.118119999766
                ],
                [
                    1583.379519999959,
                    1085.591719999909
                ],
                [
                    1619.553119999357,
                    1076.958120000549
                ],
                [
                    1644.255520000122,
                    1070.889320000075
                ],
                [
                    1684.984319999814,
                    1060.882919999771
                ],
                [
                    1762.160319999792,
                    1039.938920000568
                ],
                [
                    1987.86352000013,
                    981.3549199998379
                ],
                [
                    2014.413119999692,
                    969.8429200006649
                ],
                [
                    2021.872320000082,
                    1001.621319999918
                ],
                [
                    2184.009920000099,
                    957.81172000058
                ],
                [
                    2228.11391999945,
                    946.0021200003102
                ],
                [
                    2285.513119999319,
                    981.3989200005308
                ],
                [
                    1893.890719999559,
                    1127.877280000597
                ],
                [
                    1831.791439999826,
                    1410.598799999803
                ],
                [
                    1833.601919999346,
                    1530.567040000111
                ],
                [
                    1953.570199999958,
                    1528.756560000591
                ],
                [
                    2073.538439999335,
                    1526.94608000014
                ],
                [
                    2071.727959999815,
                    1406.977839999832
                ],
                [
                    1893.890719999559,
                    1127.877280000597
                ]
            ]
        },
        {
            "ID": "4",
            "IMAGE_ID": "Dongnae_300_1_00065",
            "CATEGORY_ID": "Dongnae_300_1_00065",
            "SEGMENTATION": "폴리곤",
            "COORDINATE": [
                [
                    2400.0,
                    603.1550000002608
                ],
                [
                    2400.0,
                    762.8076400002465
                ],
                [
                    2361.698719999753,
                    621.4781200001016
                ],
                [
                    2349.583519999869,
                    576.1629200000316
                ],
                [
                    2352.58844000008,
                    575.330880000256
                ],
                [
                    2400.0,
                    603.1550000002608
                ]
            ]
        },
        {
            "ID": "4",
            "IMAGE_ID": "Dongnae_300_1_00065",
            "CATEGORY_ID": "Dongnae_300_1_00065",
            "SEGMENTATION": "폴리곤",
            "COORDINATE": [
                [
                    2400.0,
                    847.0820000004023
                ],
                [
                    2400.0,
                    918.2774000000209
                ],
                [
                    2394.373920000158,
                    897.1589200003073
                ],
                [
                    2393.273120000027,
                    890.7477200003341
                ],
                [
                    2369.400320000015,
                    812.6549200005829
                ],
                [
                    2355.893120000139,
                    762.3725200006738
                ],
                [
                    2313.706720000133,
                    589.0197200002149
                ],
                [
                    2301.708159999922,
                    545.4710800005123
                ],
                [
                    2321.749880000018,
                    557.2328400006518
                ],
                [
                    2324.744319999591,
                    568.4301200006157
                ],
                [
                    2328.592319999821,
                    582.8109200000763
                ],
                [
                    2340.461919999681,
                    627.1981199998409
                ],
                [
                    2400.0,
                    847.0820000004023
                ]
            ]
        },
        {
            "ID": "4",
            "IMAGE_ID": "Dongnae_300_1_00065",
            "CATEGORY_ID": "Dongnae_300_1_00065",
            "SEGMENTATION": "폴리곤",
            "COORDINATE": [
                [
                    1291.619520000182,
                    1041.135720000602
                ],
                [
                    1262.881120000035,
                    1047.250119999982
                ],
                [
                    1238.561919999309,
                    1042.453320000321
                ],
                [
                    1212.918719999492,
                    941.7445200001821
                ],
                [
                    1212.206720000133,
                    940.1069200001657
                ],
                [
                    1212.206720000133,
                    937.7421200005338
                ],
                [
                    1212.937919999473,
                    935.5837200004607
                ],
                [
                    1240.830719999969,
                    886.6733200000599
                ],
                [
                    1283.986719999462,
                    813.3437200002372
                ],
                [
                    1262.666720000096,
                    727.9965200005099
                ],
                [
                    1219.375519999303,
                    558.5805200003088
                ],
                [
                    1219.374719999731,
                    557.4893200006336
                ],
                [
                    1237.217919999734,
                    533.300520000048
                ],
                [
                    1335.185920000076,
                    506.8229200001806
                ],
                [
                    1412.877919999883,
                    488.4469200000167
                ],
                [
                    1422.570720000193,
                    499.0965200001374
                ],
                [
                    1424.920319999568,
                    506.3685200000182
                ],
                [
                    1461.249919999391,
                    648.8629200002179
                ],
                [
                    1483.677919999696,
                    727.4213200006634
                ],
                [
                    1531.809119999409,
                    915.9085200000554
                ],
                [
                    1543.04591999948,
                    961.0533199999481
                ],
                [
                    1523.654719999991,
                    980.6213199999183
                ],
                [
                    1291.619520000182,
                    1041.135720000602
                ]
            ]
        },
        {
            "ID": "4",
            "IMAGE_ID": "Dongnae_300_1_00065",
            "CATEGORY_ID": "Dongnae_300_1_00065",
            "SEGMENTATION": "폴리곤",
            "COORDINATE": [
                [
                    1228.250719999894,
                    805.0141200004146
                ],
                [
                    1156.952320000157,
                    929.4893200006336
                ],
                [
                    1188.699519999325,
                    1059.965320000425
                ],
                [
                    1180.593919999897,
                    1075.926920000464
                ],
                [
                    1149.936319999397,
                    1083.748519999906
                ],
                [
                    1125.833920000121,
                    1089.900520000607
                ],
                [
                    937.9683199999854,
                    1137.842120000161
                ],
                [
                    796.9755199998617,
                    1176.375719999894
                ],
                [
                    696.982719999738,
                    1197.557320000604
                ],
                [
                    656.5115200001746,
                    1187.440520000644
                ],
                [
                    608.2451200000942,
                    1160.930120000616
                ],
                [
                    603.5387199996039,
                    1131.546120000072
                ],
                [
                    653.6243199994788,
                    1036.677319999784
                ],
                [
                    628.4731200002134,
                    1022.349320000038
                ],
                [
                    578.8883199999109,
                    1108.76292000059
                ],
                [
                    525.0115200001746,
                    1091.435720000416
                ],
                [
                    522.6435199994594,
                    1085.596520000137
                ],
                [
                    504.4411199996248,
                    1021.765320000239
                ],
                [
                    500.2139200000092,
                    1006.946120000444
                ],
                [
                    495.833920000121,
                    988.3725200006738
                ],
                [
                    465.979519999586,
                    861.7397199999541
                ],
                [
                    467.4467199994251,
                    857.7253200002015
                ],
                [
                    498.9355199998245,
                    807.4885200001299
                ],
                [
                    513.169119999744,
                    816.6213199999183
                ],
                [
                    581.8123199995607,
                    700.4333199998364
                ],
                [
                    616.8499199999496,
                    639.6589200003073
                ],
                [
                    611.169119999744,
                    637.9965200005099
                ],
                [
                    707.2899199994281,
                    470.2533200001344
                ],
                [
                    846.7971199993044,
                    433.7125200005248
                ],
                [
                    852.0275200000033,
                    420.6541200000793
                ],
                [
                    853.3075199993327,
                    418.4549200003967
                ],
                [
                    1066.29311999958,
                    542.6149200005457
                ],
                [
                    1091.043519999832,
                    581.609319999814
                ],
                [
                    1183.538719999604,
                    635.5829199999571
                ],
                [
                    1228.250719999894,
                    805.0141200004146
                ]
            ]
        },
        {
            "ID": "4",
            "IMAGE_ID": "Dongnae_300_1_00065",
            "CATEGORY_ID": "Dongnae_300_1_00065",
            "SEGMENTATION": "폴리곤",
            "COORDINATE": [
                [
                    1717.124319999479,
                    220.3573200004175
                ],
                [
                    1769.961919999681,
                    252.3781200004742
                ],
                [
                    1816.074719999917,
                    272.9461200004444
                ],
                [
                    1856.411519999616,
                    280.808520000428
                ],
                [
                    1897.753920000046,
                    281.0645200004801
                ],
                [
                    1937.797119999304,
                    271.0365200005472
                ],
                [
                    2047.103519999422,
                    240.9797200001776
                ],
                [
                    2057.359519999474,
                    239.1645200001076
                ],
                [
                    2061.183519999497,
                    239.1669199997559
                ],
                [
                    2067.221119999886,
                    239.5445199999958
                ],
                [
                    2071.033119999804,
                    239.5509200002998
                ],
                [
                    2083.800319999456,
                    246.1613199999556
                ],
                [
                    2097.852319999598,
                    259.1693200003356
                ],
                [
                    2102.536319999956,
                    268.9261199999601
                ],
                [
                    2139.253119999543,
                    401.6877199998125
                ],
                [
                    2145.234639999457,
                    425.8063599998131
                ],
                [
                    2119.3981599994,
                    438.4798800004646
                ],
                [
                    2153.314319999889,
                    458.3840399999171
                ],
                [
                    2157.022719999775,
                    473.3365200003609
                ],
                [
                    2203.773919999599,
                    661.8437200002372
                ],
                [
                    2234.567520000041,
                    771.1789199998602
                ],
                [
                    2234.753560000099,
                    773.257840000093
                ],
                [
                    2193.448199999519,
                    794.3667999999598
                ],
                [
                    2072.882720000111,
                    823.7813200000674
                ],
                [
                    1794.681919999421,
                    902.5653200000525
                ],
                [
                    1670.44927999936,
                    931.5335200000554
                ],
                [
                    1663.117279999889,
                    906.8563200002536
                ],
                [
                    1630.066199999303,
                    940.9190400000662
                ],
                [
                    1626.060320000164,
                    941.2597200004384
                ],
                [
                    1624.433120000176,
                    941.0733200004324
                ],
                [
                    1623.706720000133,
                    940.8885200005025
                ],
                [
                    1622.057919999585,
                    939.7853199997917
                ],
                [
                    1600.201119999401,
                    869.1781200002879
                ],
                [
                    1556.599519999698,
                    708.3421200001612
                ],
                [
                    1520.969920000061,
                    573.808520000428
                ],
                [
                    1500.529919999652,
                    478.0517199998721
                ],
                [
                    1500.541919999756,
                    468.2365199998021
                ],
                [
                    1501.461120000109,
                    464.2589199999347
                ],
                [
                    1526.05391999986,
                    423.0053200004622
                ],
                [
                    1612.976319999434,
                    274.6749200001359
                ],
                [
                    1647.79311999958,
                    228.1181199997663
                ],
                [
                    1648.710719999857,
                    227.7533200001344
                ],
                [
                    1650.524319999851,
                    228.1261200001463
                ],
                [
                    1717.124319999479,
                    220.3573200004175
                ]
            ]
        },
        {
            "ID": "4",
            "IMAGE_ID": "Dongnae_300_1_00065",
            "CATEGORY_ID": "Dongnae_300_1_00065",
            "SEGMENTATION": "폴리곤",
            "COORDINATE": [
                [
                    2271.07620000001,
                    364.0776399997994
                ],
                [
                    2254.461360000074,
                    372.227640000172
                ],
                [
                    2218.406719999388,
                    236.8429200006649
                ],
                [
                    2207.553519999608,
                    195.6669199997559
                ],
                [
                    2205.965919999406,
                    189.6425200002268
                ],
                [
                    2208.530720000155,
                    185.6589200003073
                ],
                [
                    2210.999119999819,
                    183.4873200003058
                ],
                [
                    2213.767519999295,
                    182.0453200004995
                ],
                [
                    2217.081519999541,
                    181.5253200000152
                ],
                [
                    2221.089920000173,
                    182.1213199999183
                ],
                [
                    2222.623119999655,
                    183.5425200005993
                ],
                [
                    2223.144719999284,
                    184.0261200005189
                ],
                [
                    2258.280319999903,
                    316.5781200006604
                ],
                [
                    2271.07620000001,
                    364.0776399997994
                ]
            ]
        },
        {
            "ID": "4",
            "IMAGE_ID": "Dongnae_300_1_00065",
            "CATEGORY_ID": "Dongnae_300_1_00065",
            "SEGMENTATION": "폴리곤",
            "COORDINATE": [
                [
                    2400.0,
                    300.836959999986
                ],
                [
                    2294.080679999664,
                    352.7932799998671
                ],
                [
                    2248.659119999968,
                    179.8489199997857
                ],
                [
                    2256.257919999771,
                    166.204119999893
                ],
                [
                    2400.0,
                    129.397520000115
                ],
                [
                    2400.0,
                    300.836959999986
                ]
            ]
        },
        {
            "ID": "4",
            "IMAGE_ID": "Dongnae_300_1_00065",
            "CATEGORY_ID": "Dongnae_300_1_00065",
            "SEGMENTATION": "폴리곤",
            "COORDINATE": [
                [
                    61.40591999981552,
                    1105.764520000666
                ],
                [
                    0.0,
                    1121.616640000604
                ],
                [
                    0.0,
                    0.0
                ],
                [
                    126.5775600001216,
                    0.0
                ],
                [
                    157.015519999899,
                    123.6069200001657
                ],
                [
                    201.2131199995056,
                    293.7501199999824
                ],
                [
                    229.1635199999437,
                    411.3997200001031
                ],
                [
                    247.0771199995652,
                    468.5341199999675
                ],
                [
                    304.4579199999571,
                    693.1325200004503
                ],
                [
                    344.6523199994117,
                    853.0109200002626
                ],
                [
                    362.1139199994504,
                    927.8405200000852
                ],
                [
                    384.8035199996084,
                    1025.066120000556
                ],
                [
                    162.3683199994266,
                    1078.03732000012
                ],
                [
                    61.40591999981552,
                    1105.764520000666
                ]
            ]
        },
        {
            "ID": "4",
            "IMAGE_ID": "Dongnae_300_1_00065",
            "CATEGORY_ID": "Dongnae_300_1_00065",
            "SEGMENTATION": "폴리곤",
            "COORDINATE": [
                [
                    529.5427199993283,
                    437.0373200001195
                ],
                [
                    490.5339199993759,
                    470.2485199999064
                ],
                [
                    488.1811199998483,
                    472.0517199998721
                ],
                [
                    486.3723200000823,
                    472.7669200003147
                ],
                [
                    482.9075199998915,
                    472.2197200004011
                ],
                [
                    477.7643200000748,
                    470.9245199998841
                ],
                [
                    457.5675200000405,
                    459.1341200005263
                ],
                [
                    412.5051199998707,
                    477.7133200000972
                ],
                [
                    398.2307199994102,
                    481.7165200002491
                ],
                [
                    412.0683199996129,
                    542.2861200002953
                ],
                [
                    418.7507199998945,
                    586.7197200004011
                ],
                [
                    422.0315199997276,
                    601.929320000112
                ],
                [
                    442.6123199993744,
                    595.8949199998751
                ],
                [
                    440.1547199999914,
                    578.5517199998721
                ],
                [
                    486.3451199997216,
                    555.4565200004727
                ],
                [
                    522.7627199999988,
                    518.3725200006738
                ],
                [
                    549.9451199993491,
                    487.0661200005561
                ],
                [
                    687.7707199994475,
                    341.2277199998498
                ],
                [
                    704.1139199994504,
                    322.9029200002551
                ],
                [
                    705.9347199993208,
                    322.7189199998975
                ],
                [
                    708.490720000118,
                    322.7245200006291
                ],
                [
                    709.2131199995056,
                    323.6413200004026
                ],
                [
                    709.7587199993432,
                    325.8453200003132
                ],
                [
                    633.8019199995324,
                    451.8061199998483
                ],
                [
                    502.7843199996278,
                    672.9277200000361
                ],
                [
                    460.7531199995428,
                    749.983719999902
                ],
                [
                    458.7563199996948,
                    750.7133200000972
                ],
                [
                    455.665919999592,
                    751.0749200005084
                ],
                [
                    448.5475199995562,
                    750.8797200005502
                ],
                [
                    444.1699199993163,
                    748.1413200004026
                ],
                [
                    427.353919999674,
                    679.465320000425
                ],
                [
                    406.9019200000912,
                    591.4013200001791
                ],
                [
                    391.189119999297,
                    543.5693199997768
                ],
                [
                    325.9435200002044,
                    290.1877199998125
                ],
                [
                    288.6635199999437,
                    139.3397200005129
                ],
                [
                    263.7043199995533,
                    41.58372000046074
                ],
                [
                    253.408239999786,
                    0.0
                ],
                [
                    638.0349599998444,
                    0.0
                ],
                [
                    698.8835199996829,
                    244.272520000115
                ],
                [
                    698.6963200001046,
                    245.9029200002551
                ],
                [
                    696.8547200001776,
                    250.0829199999571
                ],
                [
                    695.0403199996799,
                    253.3381200004369
                ],
                [
                    677.5395200001076,
                    271.5253200000152
                ],
                [
                    580.2163199996576,
                    382.1381200002506
                ],
                [
                    529.5427199993283,
                    437.0373200001195
                ]
            ]
        },
        {
            "ID": "4",
            "IMAGE_ID": "Dongnae_300_1_00065",
            "CATEGORY_ID": "Dongnae_300_1_00065",
            "SEGMENTATION": "폴리곤",
            "COORDINATE": [
                [
                    1104.906719999388,
                    463.6485200002789
                ],
                [
                    1100.736320000142,
                    464.0029199998826
                ],
                [
                    1098.039520000108,
                    463.6397200003266
                ],
                [
                    1078.509920000099,
                    453.6829200005159
                ],
                [
                    1024.488319999538,
                    427.2421200005338
                ],
                [
                    946.5675200000405,
                    376.8573200004175
                ],
                [
                    921.9915199996904,
                    360.6685199998319
                ],
                [
                    837.2595199998468,
                    303.1861200006679
                ],
                [
                    815.2683199997991,
                    266.3781200004742
                ],
                [
                    807.169119999744,
                    232.7469199998304
                ],
                [
                    799.7067200001329,
                    201.7685200003907
                ],
                [
                    793.667519999668,
                    176.7005200004205
                ],
                [
                    751.106279999949,
                    0.0
                ],
                [
                    1567.559159999713,
                    0.0
                ],
                [
                    1585.502719999291,
                    60.65732000023127
                ],
                [
                    1591.265920000151,
                    98.25332000013441
                ],
                [
                    1590.533919999376,
                    101.7125200005248
                ],
                [
                    1511.221919999458,
                    232.1357200006023
                ],
                [
                    1491.333920000121,
                    272.6229199999943
                ],
                [
                    1454.642719999887,
                    334.6501200003549
                ],
                [
                    1425.425919999368,
                    378.2421200005338
                ],
                [
                    1423.221119999886,
                    379.5229200003669
                ],
                [
                    1397.261919999495,
                    386.6501200003549
                ],
                [
                    1281.841119999997,
                    418.3517200006172
                ],
                [
                    1250.289919999428,
                    427.8749200003222
                ],
                [
                    1178.054719999433,
                    446.0645200004801
                ],
                [
                    1111.060320000164,
                    462.935720000416
                ],
                [
                    1104.906719999388,
                    463.6485200002789
                ]
            ]
        },
        {
            "ID": "4",
            "IMAGE_ID": "Dongnae_300_1_00065",
            "CATEGORY_ID": "Dongnae_300_1_00065",
            "SEGMENTATION": "폴리곤",
            "COORDINATE": [
                [
                    1881.018720000051,
                    184.3485200004652
                ],
                [
                    1874.093919999897,
                    185.7933200001717
                ],
                [
                    1866.037119999528,
                    185.778920000419
                ],
                [
                    1828.459520000033,
                    169.9421199997887
                ],
                [
                    1790.128320000134,
                    152.4381200000644
                ],
                [
                    1734.290719999932,
                    138.3813200006261
                ],
                [
                    1678.465119999833,
                    111.6605200003833
                ],
                [
                    1660.395519999787,
                    44.69892000034451
                ],
                [
                    1648.334759999998,
                    0.0
                ],
                [
                    2031.618999999948,
                    0.0
                ],
                [
                    2043.042719999328,
                    41.623720000498
                ],
                [
                    2055.868319999427,
                    96.90932000055909
                ],
                [
                    2056.41232000012,
                    102.7365199998021
                ],
                [
                    2056.406719999388,
                    105.272520000115
                ],
                [
                    2053.293920000084,
                    114.2189199998975
                ],
                [
                    2036.900320000015,
                    137.9501200001687
                ],
                [
                    2032.538719999604,
                    141.2197200004011
                ],
                [
                    2027.041919999756,
                    145.965320000425
                ],
                [
                    2023.265119999647,
                    147.7629200005904
                ],
                [
                    1946.751519999467,
                    167.5893200002611
                ],
                [
                    1881.018720000051,
                    184.3485200004652
                ]
            ]
        },
        {
            "ID": "4",
            "IMAGE_ID": "Dongnae_300_1_00065",
            "CATEGORY_ID": "Dongnae_300_1_00065",
            "SEGMENTATION": "폴리곤",
            "COORDINATE": [
                [
                    2201.302319999784,
                    139.5537200002
                ],
                [
                    2198.765920000151,
                    139.7245200006291
                ],
                [
                    2196.859120000154,
                    139.4013200001791
                ],
                [
                    2192.307519999333,
                    137.8245200002566
                ],
                [
                    2183.056319999509,
                    102.7253200002015
                ],
                [
                    2162.767519999295,
                    25.74531999975443
                ],
                [
                    2155.190479999408,
                    0.0
                ],
                [
                    2174.669400000013,
                    0.0
                ],
                [
                    2210.487519999966,
                    133.5197200002149
                ],
                [
                    2209.54871999938,
                    134.6069200001657
                ],
                [
                    2207.476719999686,
                    137.0049200002104
                ],
                [
                    2204.761520000175,
                    138.8861199999228
                ],
                [
                    2201.302319999784,
                    139.5537200002
                ]
            ]
        },
        {
            "ID": "4",
            "IMAGE_ID": "Dongnae_300_1_00065",
            "CATEGORY_ID": "Dongnae_300_1_00065",
            "SEGMENTATION": "폴리곤",
            "COORDINATE": [
                [
                    2398.117359999567,
                    90.72200000006706
                ],
                [
                    2244.535120000131,
                    132.1481200000271
                ],
                [
                    2232.881519999355,
                    125.1913200002164
                ],
                [
                    2198.784679999575,
                    0.0
                ],
                [
                    2252.862479999661,
                    0.0
                ],
                [
                    2398.117359999567,
                    90.72200000006706
                ]
            ]
        }
    ]
}