{
    "INFO": {
        "NAME": "Suyeong_198_100_00198",
        "DATA_CREATED": "2023-10-13",
        "DESCRIPTION": "없음",
        "URL": "https://safecity.busan.go.kr",
        "1HR_RAINFALL": 111.35,
        "RAINFALLOBSERVATION_POSITION": "부산",
        "RIVEROBSERVATION_POSITION": "없음",
        "BRIDGE_NAME": "없음",
        "TIDEOBSERVATION_POSITION": "부산항",
        "OBSERVATIONAL_TIDE": 0.735,
        "24HR_RAINFALL": 354.39
    },
    "CATEGORIES": {
        "ID": "Suyeong_198_100_00198",
        "NAME": "Suyeong_100",
        "CATEGORY": 2
    },
    "IMAGE": {
        "ID": "Suyeong_198_100_00198",
        "WIDTH": "2400",
        "HEIGHT": "1600",
        "FILE_NAME": "Suyeong_198_100_00198"
    },
    "ANNOTATIONS": [
        {
            "ID": "5",
            "IMAGE_ID": "Suyeong_198_100_00198",
            "CATEGORY_ID": "Suyeong_198_100_00198",
            "SEGMENTATION": "폴리곤",
            "COORDINATE": [
                [
                    102.082159999758,
                    140.376279999502
                ],
                [
                    0.0,
                    193.251119999215
                ],
                [
                    0.0,
                    168.4790399996564
                ],
                [
                    91.96775999944657,
                    120.8442799998447
                ],
                [
                    102.082159999758,
                    140.376279999502
                ]
            ]
        },
        {
            "ID": "5",
            "IMAGE_ID": "Suyeong_198_100_00198",
            "CATEGORY_ID": "Suyeong_198_100_00198",
            "SEGMENTATION": "폴리곤",
            "COORDINATE": [
                [
                    229.3801999995485,
                    0.0
                ],
                [
                    283.5673599997535,
                    102.0106799993664
                ],
                [
                    286.8785599991679,
                    129.7482799999416
                ],
                [
                    320.8125599995255,
                    194.6938799992204
                ],
                [
                    361.2165599996224,
                    272.0634800000116
                ],
                [
                    368.5501599991694,
                    287.1210799999535
                ],
                [
                    421.8333599995822,
                    396.1290799994022
                ],
                [
                    448.1789599992335,
                    448.4174799993634
                ],
                [
                    456.1909599993378,
                    465.1670800000429
                ],
                [
                    471.27015999984,
                    497.1942799994722
                ],
                [
                    476.3445599991828,
                    507.966279999353
                ],
                [
                    521.0213599996641,
                    606.1942799994722
                ],
                [
                    551.9117599995807,
                    680.6102799996734
                ],
                [
                    556.5405599996448,
                    691.5758799994364
                ],
                [
                    572.2165599996224,
                    728.702680000104
                ],
                [
                    582.5621599992737,
                    753.2106799995527
                ],
                [
                    593.6573599996045,
                    781.7946799993515
                ],
                [
                    608.1525599993765,
                    823.1386799998581
                ],
                [
                    624.6717599993572,
                    876.1242800001055
                ],
                [
                    636.8853599997237,
                    918.6826799996197
                ],
                [
                    644.9621599996462,
                    960.1010799994692
                ],
                [
                    667.3037599995732,
                    1058.045880000107
                ],
                [
                    694.2597599998116,
                    1167.545479999855
                ],
                [
                    701.7509599998593,
                    1197.971880000085
                ],
                [
                    716.7061599995941,
                    1258.716679999605
                ],
                [
                    760.3869599997997,
                    1419.713879999705
                ],
                [
                    766.5781600000337,
                    1442.536279999651
                ],
                [
                    766.6605599997565,
                    1442.84028000012
                ],
                [
                    714.7209599995986,
                    1442.84028000012
                ],
                [
                    714.7209599995986,
                    1562.84028000012
                ],
                [
                    714.7209599995986,
                    1600.0
                ],
                [
                    682.4725999999791,
                    1600.0
                ],
                [
                    651.9277599994093,
                    1484.101079999469
                ],
                [
                    641.5605599991977,
                    1486.505079999566
                ],
                [
                    630.914159999229,
                    1491.12587999925
                ],
                [
                    448.0405599996448,
                    1582.231479999609
                ],
                [
                    447.3477599993348,
                    1584.825879999436
                ],
                [
                    447.8925599996001,
                    1588.289079999551
                ],
                [
                    453.9228799995035,
                    1600.0
                ],
                [
                    363.9893199997023,
                    1600.0
                ],
                [
                    396.8221599999815,
                    1582.799479999579
                ],
                [
                    297.9433599999174,
                    1389.170679999515
                ],
                [
                    0.0,
                    1542.68519999925
                ],
                [
                    0.0,
                    1517.943559999578
                ],
                [
                    286.4913599994034,
                    1370.329079999588
                ],
                [
                    224.3853599997237,
                    1239.944679999724
                ],
                [
                    201.5781600000337,
                    1205.772679999471
                ],
                [
                    186.1341599998996,
                    1198.343080000021
                ],
                [
                    156.265359999612,
                    1192.669479999691
                ],
                [
                    104.8557599997148,
                    1219.303879999556
                ],
                [
                    61.42855999991298,
                    1241.807079999708
                ],
                [
                    0.0,
                    1274.163599999622
                ],
                [
                    0.0,
                    1246.772520000115
                ],
                [
                    58.7349600000307,
                    1216.224679999985
                ],
                [
                    59.51975999958813,
                    1214.896679999307
                ],
                [
                    45.87575999926776,
                    1209.914279999211
                ],
                [
                    0.0,
                    1233.553119999357
                ],
                [
                    0.0,
                    1206.88599999994
                ],
                [
                    47.10135999973863,
                    1182.448679999448
                ],
                [
                    86.23255999945104,
                    1167.346279999241
                ],
                [
                    112.4397599995136,
                    1157.231079999357
                ],
                [
                    115.3037599995732,
                    1155.943079999648
                ],
                [
                    142.8685599993914,
                    1143.552679999731
                ],
                [
                    144.4605599995703,
                    1137.188679999672
                ],
                [
                    60.78055999986827,
                    974.8298800000921
                ],
                [
                    46.83256000000983,
                    947.7722799992189
                ],
                [
                    0.0,
                    856.9059600001201
                ],
                [
                    0.0,
                    708.1682799998671
                ],
                [
                    165.0581599995494,
                    623.7766800001264
                ],
                [
                    137.3205599999055,
                    569.2598799997941
                ],
                [
                    148.0141599997878,
                    563.8182799993083
                ],
                [
                    175.7429599994794,
                    618.31587999966
                ],
                [
                    245.3685599993914,
                    582.7174800001085
                ],
                [
                    288.6777599994093,
                    560.8086799997836
                ],
                [
                    254.232559999451,
                    493.3414799999446
                ],
                [
                    264.917359999381,
                    487.8846799992025
                ],
                [
                    299.3837599996477,
                    555.3910799995065
                ],
                [
                    341.6845599999651,
                    533.9934799997136
                ],
                [
                    350.9677599994466,
                    524.6766799995676
                ],
                [
                    256.3117599999532,
                    347.7770799994469
                ],
                [
                    224.2629599999636,
                    345.2602800000459
                ],
                [
                    29.60455999989063,
                    447.4830799996853
                ],
                [
                    0.0,
                    463.6131599992514
                ],
                [
                    0.0,
                    393.3193999994546
                ],
                [
                    193.6269600000232,
                    292.7634799992666
                ],
                [
                    208.7869599992409,
                    255.1442799996585
                ],
                [
                    113.1157599994913,
                    73.70307999942452
                ],
                [
                    109.3005599994212,
                    75.03747999947518
                ],
                [
                    70.15083999931812,
                    0.0
                ],
                [
                    229.3801999995485,
                    0.0
                ],
                [
                    351.575759999454,
                    550.4718800000846
                ],
                [
                    309.0549599993974,
                    572.5414799991995
                ],
                [
                    298.4425599994138,
                    578.0494799995795
                ],
                [
                    210.8133600000292,
                    623.5262799998745
                ],
                [
                    186.3005599994212,
                    636.4158799992874
                ],
                [
                    175.8077599992976,
                    641.93827999942
                ],
                [
                    8.141359999775887,
                    730.1098799994215
                ],
                [
                    31.06935999915004,
                    778.0746799996123
                ],
                [
                    107.3125599995255,
                    918.9410799993202
                ],
                [
                    339.8117599999532,
                    804.3962799999863
                ],
                [
                    406.2645600000396,
                    773.2618800001219
                ],
                [
                    452.083759999834,
                    743.6154799992219
                ],
                [
                    364.0461599994451,
                    548.9998800000176
                ],
                [
                    351.575759999454,
                    550.4718800000846
                ],
                [
                    285.8705599997193,
                    856.2202800000086
                ],
                [
                    117.1965599991381,
                    943.6234799996018
                ],
                [
                    216.395759999752,
                    1137.959079999477
                ],
                [
                    221.895759999752,
                    1135.152679999359
                ],
                [
                    274.5493599995971,
                    1107.203079999425
                ],
                [
                    529.6421599993482,
                    975.5842800000682
                ],
                [
                    509.1501599997282,
                    909.4586799992248
                ],
                [
                    461.897359999828,
                    775.8146799998358
                ],
                [
                    454.3909599995241,
                    774.3154799994081
                ],
                [
                    403.8493599994108,
                    799.0258799996227
                ],
                [
                    285.8705599997193,
                    856.2202800000086
                ],
                [
                    284.7513599991798,
                    1126.692679999396
                ],
                [
                    232.0461599994451,
                    1154.671079999767
                ],
                [
                    228.8245599996299,
                    1156.311879999936
                ],
                [
                    266.229359999299,
                    1232.609480000101
                ],
                [
                    325.6365599995479,
                    1350.058279999532
                ],
                [
                    332.2805599998683,
                    1346.615079999901
                ],
                [
                    588.1933599999174,
                    1216.820679999888
                ],
                [
                    536.8613599995151,
                    1002.022679999471
                ],
                [
                    510.5893599996343,
                    1011.534679999575
                ],
                [
                    463.1357599999756,
                    1034.650679999962
                ],
                [
                    284.7513599991798,
                    1126.692679999396
                ],
                [
                    582.1325599998236,
                    1244.558279999532
                ],
                [
                    342.3189599998295,
                    1366.186679999344
                ],
                [
                    337.4061599997804,
                    1368.731479999609
                ],
                [
                    432.3789599994197,
                    1559.831479999237
                ],
                [
                    434.4941599993035,
                    1563.1962799998
                ],
                [
                    437.2509599998593,
                    1563.030679999851
                ],
                [
                    621.6253599999472,
                    1471.173879999667
                ],
                [
                    647.606959999539,
                    1459.898679999635
                ],
                [
                    617.3445599991828,
                    1329.254279999994
                ],
                [
                    596.1701599992812,
                    1246.295880000107
                ],
                [
                    594.0677600000054,
                    1242.743079999462
                ],
                [
                    591.266959999688,
                    1242.396679999307
                ],
                [
                    582.1325599998236,
                    1244.558279999532
                ]
            ]
        },
        {
            "ID": "5",
            "IMAGE_ID": "Suyeong_198_100_00198",
            "CATEGORY_ID": "Suyeong_198_100_00198",
            "SEGMENTATION": "폴리곤",
            "COORDINATE": [
                [
                    1592.366959999315,
                    2.457479999400675
                ],
                [
                    1543.515759999864,
                    44.0614799996838
                ],
                [
                    1543.442159999162,
                    66.75107999984175
                ],
                [
                    1549.935359999537,
                    89.89627999998629
                ],
                [
                    1568.216959999874,
                    138.2474799994379
                ],
                [
                    1606.503759999759,
                    239.5194799993187
                ],
                [
                    1656.11815999914,
                    368.0170799996704
                ],
                [
                    1668.279759999365,
                    398.6922800000757
                ],
                [
                    1697.042959999293,
                    471.2406799998134
                ],
                [
                    1708.535759999417,
                    492.5758799994364
                ],
                [
                    1727.043759999797,
                    542.6998799992725
                ],
                [
                    1737.723759999499,
                    571.6334799993783
                ],
                [
                    1758.330959999934,
                    625.1582800000906
                ],
                [
                    1781.942959999666,
                    694.8878799993545
                ],
                [
                    1807.210959999822,
                    769.9730799999088
                ],
                [
                    1854.687759999186,
                    895.4186800001189
                ],
                [
                    1922.083759999834,
                    1078.217480000108
                ],
                [
                    1972.01735999994,
                    1210.395079999231
                ],
                [
                    2027.054959999397,
                    1358.05227999948
                ],
                [
                    2054.3869599998,
                    1424.351479999721
                ],
                [
                    2089.698959999718,
                    1519.541079999879
                ],
                [
                    2096.288559999317,
                    1540.649079999886
                ],
                [
                    2118.981319999322,
                    1600.0
                ],
                [
                    1783.597199999727,
                    1600.0
                ],
                [
                    1780.823759999126,
                    1592.638679999858
                ],
                [
                    1794.083759999834,
                    1586.343479999341
                ],
                [
                    1774.092559999786,
                    1524.046319999732
                ],
                [
                    1828.412479999475,
                    1502.84028000012
                ],
                [
                    1758.533319999464,
                    1475.559959999286
                ],
                [
                    1749.446159999818,
                    1447.24267999921
                ],
                [
                    1707.303759999573,
                    1338.066279999912
                ],
                [
                    1674.720959999599,
                    1241.355080000125
                ],
                [
                    1674.720959999599,
                    1202.84028000012
                ],
                [
                    1661.657759999856,
                    1202.84028000012
                ],
                [
                    1624.882159999572,
                    1094.482280000113
                ],
                [
                    1574.636559999548,
                    954.0266800001264
                ],
                [
                    1554.720959999599,
                    897.7914799991995
                ],
                [
                    1554.720959999599,
                    842.8402800001204
                ],
                [
                    1554.720959999599,
                    722.8402800001204
                ],
                [
                    1554.720959999599,
                    602.8402800001204
                ],
                [
                    1464.238559999503,
                    602.8402800001204
                ],
                [
                    1434.720959999599,
                    484.7746799997985
                ],
                [
                    1434.720959999599,
                    447.3026799997315
                ],
                [
                    1435.395759999752,
                    447.6414799997583
                ],
                [
                    1442.090159999207,
                    447.8726800000295
                ],
                [
                    1434.720959999599,
                    402.1982800001279
                ],
                [
                    1434.720959999599,
                    362.8402800001204
                ],
                [
                    1434.720959999599,
                    122.8402800001204
                ],
                [
                    1434.720959999599,
                    2.840280000120401
                ],
                [
                    1334.06095999945,
                    2.840280000120401
                ],
                [
                    1333.47771999985,
                    0.0
                ],
                [
                    1595.921719999984,
                    0.0
                ],
                [
                    1592.366959999315,
                    2.457479999400675
                ]
            ]
        },
        {
            "ID": "5",
            "IMAGE_ID": "Suyeong_198_100_00198",
            "CATEGORY_ID": "Suyeong_198_100_00198",
            "SEGMENTATION": "폴리곤",
            "COORDINATE": [
                [
                    2197.774559999816,
                    128.0650800000876
                ],
                [
                    2211.408559999429,
                    151.534679999575
                ],
                [
                    2220.375759999268,
                    147.727479999885
                ],
                [
                    2254.512559999712,
                    205.9514799993485
                ],
                [
                    2281.388559999876,
                    268.0034799994901
                ],
                [
                    2338.603759999387,
                    366.6634799996391
                ],
                [
                    2365.988559999503,
                    413.876279999502
                ],
                [
                    2376.476559999399,
                    431.9626799998805
                ],
                [
                    2400.0,
                    465.1952399993315
                ],
                [
                    2400.0,
                    764.3938799994066
                ],
                [
                    2227.976559999399,
                    503.6582800000906
                ],
                [
                    2135.178959999233,
                    562.477479999885
                ],
                [
                    2109.304559999146,
                    517.5438799997792
                ],
                [
                    2203.330559999682,
                    458.13107999973
                ],
                [
                    2032.985359999351,
                    154.2106799995527
                ],
                [
                    1947.591319999658,
                    0.0
                ],
                [
                    2127.195319999941,
                    0.0
                ],
                [
                    2157.179759999737,
                    41.12227999977767
                ],
                [
                    2179.99575999938,
                    76.93427999969572
                ],
                [
                    2197.774559999816,
                    128.0650800000876
                ]
            ]
        },
        {
            "ID": "4",
            "IMAGE_ID": "Suyeong_198_100_00198",
            "CATEGORY_ID": "Suyeong_198_100_00198",
            "SEGMENTATION": "폴리곤",
            "COORDINATE": [
                [
                    1783.597199999727,
                    1600.0
                ],
                [
                    1674.720959999599,
                    1600.0
                ],
                [
                    1674.720959999599,
                    1562.84028000012
                ],
                [
                    1774.092559999786,
                    1524.046319999732
                ],
                [
                    1794.083759999834,
                    1586.343479999341
                ],
                [
                    1780.823759999126,
                    1592.638679999858
                ],
                [
                    1783.597199999727,
                    1600.0
                ]
            ]
        },
        {
            "ID": "4",
            "IMAGE_ID": "Suyeong_198_100_00198",
            "CATEGORY_ID": "Suyeong_198_100_00198",
            "SEGMENTATION": "폴리곤",
            "COORDINATE": [
                [
                    682.4725999999791,
                    1600.0
                ],
                [
                    453.9228799995035,
                    1600.0
                ],
                [
                    447.8925599996001,
                    1588.289079999551
                ],
                [
                    447.3477599993348,
                    1584.825879999436
                ],
                [
                    448.0405599996448,
                    1582.231479999609
                ],
                [
                    630.914159999229,
                    1491.12587999925
                ],
                [
                    641.5605599991977,
                    1486.505079999566
                ],
                [
                    651.9277599994093,
                    1484.101079999469
                ],
                [
                    682.4725999999791,
                    1600.0
                ]
            ]
        },
        {
            "ID": "4",
            "IMAGE_ID": "Suyeong_198_100_00198",
            "CATEGORY_ID": "Suyeong_198_100_00198",
            "SEGMENTATION": "폴리곤",
            "COORDINATE": [
                [
                    363.9893199997023,
                    1600.0
                ],
                [
                    0.0,
                    1600.0
                ],
                [
                    0.0,
                    1542.68519999925
                ],
                [
                    297.9433599999174,
                    1389.170679999515
                ],
                [
                    396.8221599999815,
                    1582.799479999579
                ],
                [
                    363.9893199997023,
                    1600.0
                ]
            ]
        },
        {
            "ID": "4",
            "IMAGE_ID": "Suyeong_198_100_00198",
            "CATEGORY_ID": "Suyeong_198_100_00198",
            "SEGMENTATION": "폴리곤",
            "COORDINATE": [
                [
                    437.2509599998593,
                    1563.030679999851
                ],
                [
                    434.4941599993035,
                    1563.1962799998
                ],
                [
                    432.3789599994197,
                    1559.831479999237
                ],
                [
                    337.4061599997804,
                    1368.731479999609
                ],
                [
                    342.3189599998295,
                    1366.186679999344
                ],
                [
                    582.1325599998236,
                    1244.558279999532
                ],
                [
                    591.266959999688,
                    1242.396679999307
                ],
                [
                    594.0677600000054,
                    1242.743079999462
                ],
                [
                    596.1701599992812,
                    1246.295880000107
                ],
                [
                    617.3445599991828,
                    1329.254279999994
                ],
                [
                    647.606959999539,
                    1459.898679999635
                ],
                [
                    621.6253599999472,
                    1471.173879999667
                ],
                [
                    437.2509599998593,
                    1563.030679999851
                ]
            ]
        },
        {
            "ID": "4",
            "IMAGE_ID": "Suyeong_198_100_00198",
            "CATEGORY_ID": "Suyeong_198_100_00198",
            "SEGMENTATION": "폴리곤",
            "COORDINATE": [
                [
                    1749.446159999818,
                    1447.24267999921
                ],
                [
                    1758.533319999464,
                    1475.559959999286
                ],
                [
                    1674.720959999599,
                    1442.84028000012
                ],
                [
                    1674.720959999599,
                    1322.84028000012
                ],
                [
                    1674.720959999599,
                    1241.355080000125
                ],
                [
                    1707.303759999573,
                    1338.066279999912
                ],
                [
                    1749.446159999818,
                    1447.24267999921
                ]
            ]
        },
        {
            "ID": "4",
            "IMAGE_ID": "Suyeong_198_100_00198",
            "CATEGORY_ID": "Suyeong_198_100_00198",
            "SEGMENTATION": "폴리곤",
            "COORDINATE": [
                [
                    58.7349600000307,
                    1216.224679999985
                ],
                [
                    0.0,
                    1246.772520000115
                ],
                [
                    0.0,
                    1233.553119999357
                ],
                [
                    45.87575999926776,
                    1209.914279999211
                ],
                [
                    59.51975999958813,
                    1214.896679999307
                ],
                [
                    58.7349600000307,
                    1216.224679999985
                ]
            ]
        },
        {
            "ID": "4",
            "IMAGE_ID": "Suyeong_198_100_00198",
            "CATEGORY_ID": "Suyeong_198_100_00198",
            "SEGMENTATION": "폴리곤",
            "COORDINATE": [
                [
                    286.4913599994034,
                    1370.329079999588
                ],
                [
                    0.0,
                    1517.943559999578
                ],
                [
                    0.0,
                    1274.163599999622
                ],
                [
                    61.42855999991298,
                    1241.807079999708
                ],
                [
                    104.8557599997148,
                    1219.303879999556
                ],
                [
                    156.265359999612,
                    1192.669479999691
                ],
                [
                    186.1341599998996,
                    1198.343080000021
                ],
                [
                    201.5781600000337,
                    1205.772679999471
                ],
                [
                    224.3853599997237,
                    1239.944679999724
                ],
                [
                    286.4913599994034,
                    1370.329079999588
                ]
            ]
        },
        {
            "ID": "4",
            "IMAGE_ID": "Suyeong_198_100_00198",
            "CATEGORY_ID": "Suyeong_198_100_00198",
            "SEGMENTATION": "폴리곤",
            "COORDINATE": [
                [
                    332.2805599998683,
                    1346.615079999901
                ],
                [
                    325.6365599995479,
                    1350.058279999532
                ],
                [
                    266.229359999299,
                    1232.609480000101
                ],
                [
                    228.8245599996299,
                    1156.311879999936
                ],
                [
                    232.0461599994451,
                    1154.671079999767
                ],
                [
                    284.7513599991798,
                    1126.692679999396
                ],
                [
                    463.1357599999756,
                    1034.650679999962
                ],
                [
                    510.5893599996343,
                    1011.534679999575
                ],
                [
                    536.8613599995151,
                    1002.022679999471
                ],
                [
                    588.1933599999174,
                    1216.820679999888
                ],
                [
                    332.2805599998683,
                    1346.615079999901
                ]
            ]
        },
        {
            "ID": "4",
            "IMAGE_ID": "Suyeong_198_100_00198",
            "CATEGORY_ID": "Suyeong_198_100_00198",
            "SEGMENTATION": "폴리곤",
            "COORDINATE": [
                [
                    1661.657759999856,
                    1202.84028000012
                ],
                [
                    1554.720959999599,
                    1202.84028000012
                ],
                [
                    1554.720959999599,
                    1082.84028000012
                ],
                [
                    1554.720959999599,
                    897.7914799991995
                ],
                [
                    1574.636559999548,
                    954.0266800001264
                ],
                [
                    1624.882159999572,
                    1094.482280000113
                ],
                [
                    1661.657759999856,
                    1202.84028000012
                ]
            ]
        },
        {
            "ID": "4",
            "IMAGE_ID": "Suyeong_198_100_00198",
            "CATEGORY_ID": "Suyeong_198_100_00198",
            "SEGMENTATION": "폴리곤",
            "COORDINATE": [
                [
                    47.10135999973863,
                    1182.448679999448
                ],
                [
                    0.0,
                    1206.88599999994
                ],
                [
                    0.0,
                    856.9059600001201
                ],
                [
                    46.83256000000983,
                    947.7722799992189
                ],
                [
                    60.78055999986827,
                    974.8298800000921
                ],
                [
                    144.4605599995703,
                    1137.188679999672
                ],
                [
                    142.8685599993914,
                    1143.552679999731
                ],
                [
                    115.3037599995732,
                    1155.943079999648
                ],
                [
                    112.4397599995136,
                    1157.231079999357
                ],
                [
                    86.23255999945104,
                    1167.346279999241
                ],
                [
                    47.10135999973863,
                    1182.448679999448
                ]
            ]
        },
        {
            "ID": "4",
            "IMAGE_ID": "Suyeong_198_100_00198",
            "CATEGORY_ID": "Suyeong_198_100_00198",
            "SEGMENTATION": "폴리곤",
            "COORDINATE": [
                [
                    221.895759999752,
                    1135.152679999359
                ],
                [
                    216.395759999752,
                    1137.959079999477
                ],
                [
                    117.1965599991381,
                    943.6234799996018
                ],
                [
                    285.8705599997193,
                    856.2202800000086
                ],
                [
                    403.8493599994108,
                    799.0258799996227
                ],
                [
                    454.3909599995241,
                    774.3154799994081
                ],
                [
                    461.897359999828,
                    775.8146799998358
                ],
                [
                    509.1501599997282,
                    909.4586799992248
                ],
                [
                    529.6421599993482,
                    975.5842800000682
                ],
                [
                    274.5493599995971,
                    1107.203079999425
                ],
                [
                    221.895759999752,
                    1135.152679999359
                ]
            ]
        },
        {
            "ID": "4",
            "IMAGE_ID": "Suyeong_198_100_00198",
            "CATEGORY_ID": "Suyeong_198_100_00198",
            "SEGMENTATION": "폴리곤",
            "COORDINATE": [
                [
                    339.8117599999532,
                    804.3962799999863
                ],
                [
                    107.3125599995255,
                    918.9410799993202
                ],
                [
                    31.06935999915004,
                    778.0746799996123
                ],
                [
                    8.141359999775887,
                    730.1098799994215
                ],
                [
                    175.8077599992976,
                    641.93827999942
                ],
                [
                    186.3005599994212,
                    636.4158799992874
                ],
                [
                    210.8133600000292,
                    623.5262799998745
                ],
                [
                    298.4425599994138,
                    578.0494799995795
                ],
                [
                    309.0549599993974,
                    572.5414799991995
                ],
                [
                    351.575759999454,
                    550.4718800000846
                ],
                [
                    364.0461599994451,
                    548.9998800000176
                ],
                [
                    452.083759999834,
                    743.6154799992219
                ],
                [
                    406.2645600000396,
                    773.2618800001219
                ],
                [
                    339.8117599999532,
                    804.3962799999863
                ]
            ]
        },
        {
            "ID": "4",
            "IMAGE_ID": "Suyeong_198_100_00198",
            "CATEGORY_ID": "Suyeong_198_100_00198",
            "SEGMENTATION": "폴리곤",
            "COORDINATE": [
                [
                    1464.238559999503,
                    602.8402800001204
                ],
                [
                    1434.720959999599,
                    602.8402800001204
                ],
                [
                    1434.720959999599,
                    484.7746799997985
                ],
                [
                    1464.238559999503,
                    602.8402800001204
                ]
            ]
        },
        {
            "ID": "4",
            "IMAGE_ID": "Suyeong_198_100_00198",
            "CATEGORY_ID": "Suyeong_198_100_00198",
            "SEGMENTATION": "폴리곤",
            "COORDINATE": [
                [
                    1434.720959999599,
                    402.1982800001279
                ],
                [
                    1442.090159999207,
                    447.8726800000295
                ],
                [
                    1435.395759999752,
                    447.6414799997583
                ],
                [
                    1434.720959999599,
                    447.3026799997315
                ],
                [
                    1434.720959999599,
                    402.1982800001279
                ]
            ]
        },
        {
            "ID": "4",
            "IMAGE_ID": "Suyeong_198_100_00198",
            "CATEGORY_ID": "Suyeong_198_100_00198",
            "SEGMENTATION": "폴리곤",
            "COORDINATE": [
                [
                    256.3117599999532,
                    347.7770799994469
                ],
                [
                    350.9677599994466,
                    524.6766799995676
                ],
                [
                    341.6845599999651,
                    533.9934799997136
                ],
                [
                    299.3837599996477,
                    555.3910799995065
                ],
                [
                    264.917359999381,
                    487.8846799992025
                ],
                [
                    254.232559999451,
                    493.3414799999446
                ],
                [
                    288.6777599994093,
                    560.8086799997836
                ],
                [
                    245.3685599993914,
                    582.7174800001085
                ],
                [
                    175.7429599994794,
                    618.31587999966
                ],
                [
                    148.0141599997878,
                    563.8182799993083
                ],
                [
                    137.3205599999055,
                    569.2598799997941
                ],
                [
                    165.0581599995494,
                    623.7766800001264
                ],
                [
                    0.0,
                    708.1682799998671
                ],
                [
                    0.0,
                    463.6131599992514
                ],
                [
                    29.60455999989063,
                    447.4830799996853
                ],
                [
                    224.2629599999636,
                    345.2602800000459
                ],
                [
                    256.3117599999532,
                    347.7770799994469
                ]
            ]
        },
        {
            "ID": "4",
            "IMAGE_ID": "Suyeong_198_100_00198",
            "CATEGORY_ID": "Suyeong_198_100_00198",
            "SEGMENTATION": "폴리곤",
            "COORDINATE": [
                [
                    70.15083999931812,
                    0.0
                ],
                [
                    109.3005599994212,
                    75.03747999947518
                ],
                [
                    113.1157599994913,
                    73.70307999942452
                ],
                [
                    208.7869599992409,
                    255.1442799996585
                ],
                [
                    193.6269600000232,
                    292.7634799992666
                ],
                [
                    0.0,
                    393.3193999994546
                ],
                [
                    0.0,
                    193.251119999215
                ],
                [
                    102.082159999758,
                    140.376279999502
                ],
                [
                    91.96775999944657,
                    120.8442799998447
                ],
                [
                    0.0,
                    168.4790399996564
                ],
                [
                    0.0,
                    0.0
                ],
                [
                    70.15083999931812,
                    0.0
                ]
            ]
        },
        {
            "ID": "4",
            "IMAGE_ID": "Suyeong_198_100_00198",
            "CATEGORY_ID": "Suyeong_198_100_00198",
            "SEGMENTATION": "폴리곤",
            "COORDINATE": [
                [
                    714.7209599995986,
                    962.8402800001204
                ],
                [
                    714.7209599995986,
                    1082.84028000012
                ],
                [
                    795.3985999999568,
                    1082.84028000012
                ],
                [
                    826.4313599998131,
                    1404.599479999393
                ],
                [
                    829.1628399994224,
                    1442.84028000012
                ],
                [
                    766.6605599997565,
                    1442.84028000012
                ],
                [
                    766.5781600000337,
                    1442.536279999651
                ],
                [
                    760.3869599997997,
                    1419.713879999705
                ],
                [
                    716.7061599995941,
                    1258.716679999605
                ],
                [
                    701.7509599998593,
                    1197.971880000085
                ],
                [
                    694.2597599998116,
                    1167.545479999855
                ],
                [
                    667.3037599995732,
                    1058.045880000107
                ],
                [
                    644.9621599996462,
                    960.1010799994692
                ],
                [
                    636.8853599997237,
                    918.6826799996197
                ],
                [
                    624.6717599993572,
                    876.1242800001055
                ],
                [
                    608.1525599993765,
                    823.1386799998581
                ],
                [
                    593.6573599996045,
                    781.7946799993515
                ],
                [
                    582.5621599992737,
                    753.2106799995527
                ],
                [
                    572.2165599996224,
                    728.702680000104
                ],
                [
                    556.5405599996448,
                    691.5758799994364
                ],
                [
                    551.9117599995807,
                    680.6102799996734
                ],
                [
                    521.0213599996641,
                    606.1942799994722
                ],
                [
                    476.3445599991828,
                    507.966279999353
                ],
                [
                    471.27015999984,
                    497.1942799994722
                ],
                [
                    456.1909599993378,
                    465.1670800000429
                ],
                [
                    448.1789599992335,
                    448.4174799993634
                ],
                [
                    421.8333599995822,
                    396.1290799994022
                ],
                [
                    368.5501599991694,
                    287.1210799999535
                ],
                [
                    361.2165599996224,
                    272.0634800000116
                ],
                [
                    320.8125599995255,
                    194.6938799992204
                ],
                [
                    286.8785599991679,
                    129.7482799999416
                ],
                [
                    283.5673599997535,
                    102.0106799993664
                ],
                [
                    229.3801999995485,
                    0.0
                ],
                [
                    702.2623599991202,
                    0.0
                ],
                [
                    707.5449599996209,
                    70.21507999952883
                ],
                [
                    714.7209599995986,
                    154.2538399994373
                ],
                [
                    714.7209599995986,
                    842.8402800001204
                ],
                [
                    714.7209599995986,
                    962.8402800001204
                ]
            ]
        },
        {
            "ID": "4",
            "IMAGE_ID": "Suyeong_198_100_00198",
            "CATEGORY_ID": "Suyeong_198_100_00198",
            "SEGMENTATION": "폴리곤",
            "COORDINATE": [
                [
                    1334.06095999945,
                    2.840280000120401
                ],
                [
                    1314.720959999599,
                    2.840280000120401
                ],
                [
                    1314.720959999599,
                    0.0
                ],
                [
                    1333.47771999985,
                    0.0
                ],
                [
                    1334.06095999945,
                    2.840280000120401
                ]
            ]
        },
        {
            "ID": "4",
            "IMAGE_ID": "Suyeong_198_100_00198",
            "CATEGORY_ID": "Suyeong_198_100_00198",
            "SEGMENTATION": "폴리곤",
            "COORDINATE": [
                [
                    2109.304559999146,
                    517.5438799997792
                ],
                [
                    2135.178959999233,
                    562.477479999885
                ],
                [
                    2227.976559999399,
                    503.6582800000906
                ],
                [
                    2400.0,
                    764.3938799994066
                ],
                [
                    2400.0,
                    1600.0
                ],
                [
                    2118.981319999322,
                    1600.0
                ],
                [
                    2096.288559999317,
                    1540.649079999886
                ],
                [
                    2089.698959999718,
                    1519.541079999879
                ],
                [
                    2054.3869599998,
                    1424.351479999721
                ],
                [
                    2027.054959999397,
                    1358.05227999948
                ],
                [
                    1972.01735999994,
                    1210.395079999231
                ],
                [
                    1922.083759999834,
                    1078.217480000108
                ],
                [
                    1854.687759999186,
                    895.4186800001189
                ],
                [
                    1807.210959999822,
                    769.9730799999088
                ],
                [
                    1781.942959999666,
                    694.8878799993545
                ],
                [
                    1758.330959999934,
                    625.1582800000906
                ],
                [
                    1737.723759999499,
                    571.6334799993783
                ],
                [
                    1727.043759999797,
                    542.6998799992725
                ],
                [
                    1708.535759999417,
                    492.5758799994364
                ],
                [
                    1697.042959999293,
                    471.2406799998134
                ],
                [
                    1668.279759999365,
                    398.6922800000757
                ],
                [
                    1656.11815999914,
                    368.0170799996704
                ],
                [
                    1606.503759999759,
                    239.5194799993187
                ],
                [
                    1568.216959999874,
                    138.2474799994379
                ],
                [
                    1549.935359999537,
                    89.89627999998629
                ],
                [
                    1543.442159999162,
                    66.75107999984175
                ],
                [
                    1543.515759999864,
                    44.0614799996838
                ],
                [
                    1592.366959999315,
                    2.457479999400675
                ],
                [
                    1595.921719999984,
                    0.0
                ],
                [
                    1947.591319999658,
                    0.0
                ],
                [
                    2032.985359999351,
                    154.2106799995527
                ],
                [
                    2203.330559999682,
                    458.13107999973
                ],
                [
                    2109.304559999146,
                    517.5438799997792
                ]
            ]
        },
        {
            "ID": "4",
            "IMAGE_ID": "Suyeong_198_100_00198",
            "CATEGORY_ID": "Suyeong_198_100_00198",
            "SEGMENTATION": "폴리곤",
            "COORDINATE": [
                [
                    2400.0,
                    0.0
                ],
                [
                    2400.0,
                    465.1952399993315
                ],
                [
                    2376.476559999399,
                    431.9626799998805
                ],
                [
                    2365.988559999503,
                    413.876279999502
                ],
                [
                    2338.603759999387,
                    366.6634799996391
                ],
                [
                    2281.388559999876,
                    268.0034799994901
                ],
                [
                    2254.512559999712,
                    205.9514799993485
                ],
                [
                    2220.375759999268,
                    147.727479999885
                ],
                [
                    2211.408559999429,
                    151.534679999575
                ],
                [
                    2197.774559999816,
                    128.0650800000876
                ],
                [
                    2179.99575999938,
                    76.93427999969572
                ],
                [
                    2157.179759999737,
                    41.12227999977767
                ],
                [
                    2127.195319999941,
                    0.0
                ],
                [
                    2400.0,
                    0.0
                ]
            ]
        },
        {
            "ID": "6",
            "IMAGE_ID": "Suyeong_198_100_00198",
            "CATEGORY_ID": "Suyeong_198_100_00198",
            "SEGMENTATION": "폴리곤",
            "COORDINATE": [
                [
                    834.7209599995986,
                    1562.84028000012
                ],
                [
                    714.7209599995986,
                    1562.84028000012
                ],
                [
                    714.7209599995986,
                    1442.84028000012
                ],
                [
                    766.6605599997565,
                    1442.84028000012
                ],
                [
                    829.1628399994224,
                    1442.84028000012
                ],
                [
                    834.7209599995986,
                    1520.655079999939
                ],
                [
                    834.7209599995986,
                    1562.84028000012
                ]
            ]
        },
        {
            "ID": "6",
            "IMAGE_ID": "Suyeong_198_100_00198",
            "CATEGORY_ID": "Suyeong_198_100_00198",
            "SEGMENTATION": "폴리곤",
            "COORDINATE": [
                [
                    1774.092559999786,
                    1524.046319999732
                ],
                [
                    1674.720959999599,
                    1562.84028000012
                ],
                [
                    1674.720959999599,
                    1442.84028000012
                ],
                [
                    1758.533319999464,
                    1475.559959999286
                ],
                [
                    1828.412479999475,
                    1502.84028000012
                ],
                [
                    1774.092559999786,
                    1524.046319999732
                ]
            ]
        },
        {
            "ID": "6",
            "IMAGE_ID": "Suyeong_198_100_00198",
            "CATEGORY_ID": "Suyeong_198_100_00198",
            "SEGMENTATION": "폴리곤",
            "COORDINATE": [
                [
                    1554.720959999599,
                    722.8402800001204
                ],
                [
                    1434.720959999599,
                    722.8402800001204
                ],
                [
                    1434.720959999599,
                    602.8402800001204
                ],
                [
                    1464.238559999503,
                    602.8402800001204
                ],
                [
                    1554.720959999599,
                    602.8402800001204
                ],
                [
                    1554.720959999599,
                    722.8402800001204
                ]
            ]
        },
        {
            "ID": "6",
            "IMAGE_ID": "Suyeong_198_100_00198",
            "CATEGORY_ID": "Suyeong_198_100_00198",
            "SEGMENTATION": "폴리곤",
            "COORDINATE": [
                [
                    1434.720959999599,
                    122.8402800001204
                ],
                [
                    1314.720959999599,
                    122.8402800001204
                ],
                [
                    1314.720959999599,
                    2.840280000120401
                ],
                [
                    1334.06095999945,
                    2.840280000120401
                ],
                [
                    1434.720959999599,
                    2.840280000120401
                ],
                [
                    1434.720959999599,
                    122.8402800001204
                ]
            ]
        },
        {
            "ID": "7",
            "IMAGE_ID": "Suyeong_198_100_00198",
            "CATEGORY_ID": "Suyeong_198_100_00198",
            "SEGMENTATION": "폴리곤",
            "COORDINATE": [
                [
                    1674.720959999599,
                    1322.84028000012
                ],
                [
                    1554.720959999599,
                    1322.84028000012
                ],
                [
                    1554.720959999599,
                    1202.84028000012
                ],
                [
                    1661.657759999856,
                    1202.84028000012
                ],
                [
                    1674.720959999599,
                    1202.84028000012
                ],
                [
                    1674.720959999599,
                    1241.355080000125
                ],
                [
                    1674.720959999599,
                    1322.84028000012
                ]
            ]
        },
        {
            "ID": "7",
            "IMAGE_ID": "Suyeong_198_100_00198",
            "CATEGORY_ID": "Suyeong_198_100_00198",
            "SEGMENTATION": "폴리곤",
            "COORDINATE": [
                [
                    795.3985999999568,
                    1082.84028000012
                ],
                [
                    714.7209599995986,
                    1082.84028000012
                ],
                [
                    714.7209599995986,
                    962.8402800001204
                ],
                [
                    799.5436799991876,
                    962.8402800001204
                ],
                [
                    802.0895599992946,
                    985.4985999995843
                ],
                [
                    786.2145199999213,
                    987.6152799995616
                ],
                [
                    795.3985999999568,
                    1082.84028000012
                ]
            ]
        },
        {
            "ID": "7",
            "IMAGE_ID": "Suyeong_198_100_00198",
            "CATEGORY_ID": "Suyeong_198_100_00198",
            "SEGMENTATION": "폴리곤",
            "COORDINATE": [
                [
                    1554.720959999599,
                    842.8402800001204
                ],
                [
                    1438.170159999281,
                    842.8402800001204
                ],
                [
                    1434.720959999599,
                    824.7191599998623
                ],
                [
                    1434.720959999599,
                    722.8402800001204
                ],
                [
                    1554.720959999599,
                    722.8402800001204
                ],
                [
                    1554.720959999599,
                    842.8402800001204
                ]
            ]
        },
        {
            "ID": "7",
            "IMAGE_ID": "Suyeong_198_100_00198",
            "CATEGORY_ID": "Suyeong_198_100_00198",
            "SEGMENTATION": "폴리곤",
            "COORDINATE": [
                [
                    1314.720959999599,
                    2.840280000120401
                ],
                [
                    1276.044519999996,
                    2.840280000120401
                ],
                [
                    1274.894879999571,
                    0.0
                ],
                [
                    1314.720959999599,
                    0.0
                ],
                [
                    1314.720959999599,
                    2.840280000120401
                ]
            ]
        },
        {
            "ID": "8",
            "IMAGE_ID": "Suyeong_198_100_00198",
            "CATEGORY_ID": "Suyeong_198_100_00198",
            "SEGMENTATION": "폴리곤",
            "COORDINATE": [
                [
                    834.7209599995986,
                    1600.0
                ],
                [
                    714.7209599995986,
                    1600.0
                ],
                [
                    714.7209599995986,
                    1562.84028000012
                ],
                [
                    834.7209599995986,
                    1562.84028000012
                ],
                [
                    834.7209599995986,
                    1600.0
                ]
            ]
        },
        {
            "ID": "8",
            "IMAGE_ID": "Suyeong_198_100_00198",
            "CATEGORY_ID": "Suyeong_198_100_00198",
            "SEGMENTATION": "폴리곤",
            "COORDINATE": [
                [
                    1674.720959999599,
                    1562.84028000012
                ],
                [
                    1575.356959999539,
                    1562.84028000012
                ],
                [
                    1563.733759999275,
                    1526.209559999406
                ],
                [
                    1554.720959999599,
                    1472.338879999705
                ],
                [
                    1554.720959999599,
                    1322.84028000012
                ],
                [
                    1674.720959999599,
                    1322.84028000012
                ],
                [
                    1674.720959999599,
                    1442.84028000012
                ],
                [
                    1674.720959999599,
                    1562.84028000012
                ]
            ]
        },
        {
            "ID": "8",
            "IMAGE_ID": "Suyeong_198_100_00198",
            "CATEGORY_ID": "Suyeong_198_100_00198",
            "SEGMENTATION": "폴리곤",
            "COORDINATE": [
                [
                    773.5189600000158,
                    842.8402800001204
                ],
                [
                    777.7478399993852,
                    892.3650799999014
                ],
                [
                    791.5061999997124,
                    891.3067199997604
                ],
                [
                    799.5436799991876,
                    962.8402800001204
                ],
                [
                    714.7209599995986,
                    962.8402800001204
                ],
                [
                    714.7209599995986,
                    842.8402800001204
                ],
                [
                    773.5189600000158,
                    842.8402800001204
                ]
            ]
        },
        {
            "ID": "8",
            "IMAGE_ID": "Suyeong_198_100_00198",
            "CATEGORY_ID": "Suyeong_198_100_00198",
            "SEGMENTATION": "폴리곤",
            "COORDINATE": [
                [
                    1554.720959999599,
                    1082.84028000012
                ],
                [
                    1486.433639999479,
                    1082.84028000012
                ],
                [
                    1461.054639999755,
                    963.0692799994722
                ],
                [
                    1438.170159999281,
                    842.8402800001204
                ],
                [
                    1554.720959999599,
                    842.8402800001204
                ],
                [
                    1554.720959999599,
                    897.7914799991995
                ],
                [
                    1554.720959999599,
                    1082.84028000012
                ]
            ]
        },
        {
            "ID": "8",
            "IMAGE_ID": "Suyeong_198_100_00198",
            "CATEGORY_ID": "Suyeong_198_100_00198",
            "SEGMENTATION": "폴리곤",
            "COORDINATE": [
                [
                    1434.720959999599,
                    362.8402800001204
                ],
                [
                    1341.118479999714,
                    362.8402800001204
                ],
                [
                    1317.826599999331,
                    277.2679199995473
                ],
                [
                    1314.720959999599,
                    252.4229199998081
                ],
                [
                    1314.720959999599,
                    175.4037599992007
                ],
                [
                    1318.532159999944,
                    170.0232400000095
                ],
                [
                    1314.720959999599,
                    145.9962399993092
                ],
                [
                    1314.720959999599,
                    122.8402800001204
                ],
                [
                    1434.720959999599,
                    122.8402800001204
                ],
                [
                    1434.720959999599,
                    362.8402800001204
                ]
            ]
        },
        {
            "ID": "9",
            "IMAGE_ID": "Suyeong_198_100_00198",
            "CATEGORY_ID": "Suyeong_198_100_00198",
            "SEGMENTATION": "폴리곤",
            "COORDINATE": [
                [
                    1674.720959999599,
                    1600.0
                ],
                [
                    1587.148039999418,
                    1600.0
                ],
                [
                    1575.356959999539,
                    1562.84028000012
                ],
                [
                    1674.720959999599,
                    1562.84028000012
                ],
                [
                    1674.720959999599,
                    1600.0
                ]
            ]
        },
        {
            "ID": "9",
            "IMAGE_ID": "Suyeong_198_100_00198",
            "CATEGORY_ID": "Suyeong_198_100_00198",
            "SEGMENTATION": "폴리곤",
            "COORDINATE": [
                [
                    840.3884399998933,
                    1600.0
                ],
                [
                    834.7209599995986,
                    1600.0
                ],
                [
                    834.7209599995986,
                    1562.84028000012
                ],
                [
                    834.7209599995986,
                    1520.655079999939
                ],
                [
                    840.3884399998933,
                    1600.0
                ]
            ]
        },
        {
            "ID": "9",
            "IMAGE_ID": "Suyeong_198_100_00198",
            "CATEGORY_ID": "Suyeong_198_100_00198",
            "SEGMENTATION": "폴리곤",
            "COORDINATE": [
                [
                    1554.720959999599,
                    1322.84028000012
                ],
                [
                    1554.720959999599,
                    1472.338879999705
                ],
                [
                    1501.271399999969,
                    1152.864120000042
                ],
                [
                    1486.433639999479,
                    1082.84028000012
                ],
                [
                    1554.720959999599,
                    1082.84028000012
                ],
                [
                    1554.720959999599,
                    1202.84028000012
                ],
                [
                    1554.720959999599,
                    1322.84028000012
                ]
            ]
        },
        {
            "ID": "9",
            "IMAGE_ID": "Suyeong_198_100_00198",
            "CATEGORY_ID": "Suyeong_198_100_00198",
            "SEGMENTATION": "폴리곤",
            "COORDINATE": [
                [
                    1434.720959999599,
                    722.8402800001204
                ],
                [
                    1434.720959999599,
                    824.7191599998623
                ],
                [
                    1413.7823199993,
                    714.713239999488
                ],
                [
                    1383.443399999291,
                    576.4240799993277
                ],
                [
                    1350.282199999318,
                    396.5070399995893
                ],
                [
                    1341.118479999714,
                    362.8402800001204
                ],
                [
                    1434.720959999599,
                    362.8402800001204
                ],
                [
                    1434.720959999599,
                    402.1982800001279
                ],
                [
                    1434.720959999599,
                    447.3026799997315
                ],
                [
                    1434.720959999599,
                    484.7746799997985
                ],
                [
                    1434.720959999599,
                    602.8402800001204
                ],
                [
                    1434.720959999599,
                    722.8402800001204
                ]
            ]
        },
        {
            "ID": "9",
            "IMAGE_ID": "Suyeong_198_100_00198",
            "CATEGORY_ID": "Suyeong_198_100_00198",
            "SEGMENTATION": "폴리곤",
            "COORDINATE": [
                [
                    1314.720959999599,
                    175.4037599992007
                ],
                [
                    1314.720959999599,
                    252.4229199998081
                ],
                [
                    1306.537679999135,
                    186.9565999992192
                ],
                [
                    1314.720959999599,
                    175.4037599992007
                ]
            ]
        },
        {
            "ID": "9",
            "IMAGE_ID": "Suyeong_198_100_00198",
            "CATEGORY_ID": "Suyeong_198_100_00198",
            "SEGMENTATION": "폴리곤",
            "COORDINATE": [
                [
                    773.5189600000158,
                    842.8402800001204
                ],
                [
                    714.7209599995986,
                    842.8402800001204
                ],
                [
                    714.7209599995986,
                    154.2538399994373
                ],
                [
                    773.5189600000158,
                    842.8402800001204
                ]
            ]
        },
        {
            "ID": "9",
            "IMAGE_ID": "Suyeong_198_100_00198",
            "CATEGORY_ID": "Suyeong_198_100_00198",
            "SEGMENTATION": "폴리곤",
            "COORDINATE": [
                [
                    1314.720959999599,
                    122.8402800001204
                ],
                [
                    1314.720959999599,
                    145.9962399993092
                ],
                [
                    1302.304319999181,
                    67.71748000010848
                ],
                [
                    1276.044519999996,
                    2.840280000120401
                ],
                [
                    1314.720959999599,
                    2.840280000120401
                ],
                [
                    1314.720959999599,
                    122.8402800001204
                ]
            ]
        },
        {
            "ID": "1",
            "IMAGE_ID": "Suyeong_198_100_00198",
            "CATEGORY_ID": "Suyeong_198_100_00198",
            "SEGMENTATION": "폴리곤",
            "COORDINATE": [
                [
                    1276.044519999996,
                    2.840280000120401
                ],
                [
                    1302.304319999181,
                    67.71748000010848
                ],
                [
                    1314.720959999599,
                    145.9962399993092
                ],
                [
                    1318.532159999944,
                    170.0232400000095
                ],
                [
                    1314.720959999599,
                    175.4037599992007
                ],
                [
                    1306.537679999135,
                    186.9565999992192
                ],
                [
                    1314.720959999599,
                    252.4229199998081
                ],
                [
                    1317.826599999331,
                    277.2679199995473
                ],
                [
                    1341.118479999714,
                    362.8402800001204
                ],
                [
                    1350.282199999318,
                    396.5070399995893
                ],
                [
                    1383.443399999291,
                    576.4240799993277
                ],
                [
                    1413.7823199993,
                    714.713239999488
                ],
                [
                    1434.720959999599,
                    824.7191599998623
                ],
                [
                    1438.170159999281,
                    842.8402800001204
                ],
                [
                    1461.054639999755,
                    963.0692799994722
                ],
                [
                    1486.433639999479,
                    1082.84028000012
                ],
                [
                    1501.271399999969,
                    1152.864120000042
                ],
                [
                    1554.720959999599,
                    1472.338879999705
                ],
                [
                    1563.733759999275,
                    1526.209559999406
                ],
                [
                    1575.356959999539,
                    1562.84028000012
                ],
                [
                    1587.148039999418,
                    1600.0
                ],
                [
                    840.3884399998933,
                    1600.0
                ],
                [
                    834.7209599995986,
                    1520.655079999939
                ],
                [
                    829.1628399994224,
                    1442.84028000012
                ],
                [
                    826.4313599998131,
                    1404.599479999393
                ],
                [
                    795.3985999999568,
                    1082.84028000012
                ],
                [
                    786.2145199999213,
                    987.6152799995616
                ],
                [
                    802.0895599992946,
                    985.4985999995843
                ],
                [
                    799.5436799991876,
                    962.8402800001204
                ],
                [
                    791.5061999997124,
                    891.3067199997604
                ],
                [
                    777.7478399993852,
                    892.3650799999014
                ],
                [
                    773.5189600000158,
                    842.8402800001204
                ],
                [
                    714.7209599995986,
                    154.2538399994373
                ],
                [
                    707.5449599996209,
                    70.21507999952883
                ],
                [
                    702.2623599991202,
                    0.0
                ],
                [
                    1274.894879999571,
                    0.0
                ],
                [
                    1276.044519999996,
                    2.840280000120401
                ]
            ]
        }
    ]
}