{
    "INFO": {
        "NAME": "Oncheon_435_500_00435",
        "DATA_CREATED": "2023-08-30",
        "DESCRIPTION": "없음",
        "URL": "https://safecity.busan.go.kr",
        "1HR_RAINFALL": 145.64,
        "RAINFALLOBSERVATION_POSITION": "부산",
        "RIVEROBSERVATION_POSITION": "없음",
        "BRIDGE_NAME": "없음",
        "TIDEOBSERVATION_POSITION": "부산항",
        "OBSERVATIONAL_TIDE": 0.735,
        "24HR_RAINFALL": 433.7
    },
    "CATEGORIES": {
        "ID": "Oncheon_435_500_00435",
        "NAME": "Oncheon_500",
        "CATEGORY": 2
    },
    "IMAGE": {
        "ID": "Oncheon_435_500_00435",
        "WIDTH": "2400",
        "HEIGHT": "1600",
        "FILE_NAME": "Oncheon_435_500_00435"
    },
    "ANNOTATIONS": [
        {
            "ID": "5",
            "IMAGE_ID": "Oncheon_435_500_00435",
            "CATEGORY_ID": "Oncheon_435_500_00435",
            "SEGMENTATION": "폴리곤",
            "COORDINATE": [
                [
                    694.4575999975204,
                    1600.0
                ],
                [
                    666.666400000453,
                    1600.0
                ],
                [
                    662.9560000002384,
                    1582.660799995065
                ],
                [
                    694.0663999989629,
                    1598.215999998152
                ],
                [
                    694.4575999975204,
                    1600.0
                ]
            ]
        },
        {
            "ID": "5",
            "IMAGE_ID": "Oncheon_435_500_00435",
            "CATEGORY_ID": "Oncheon_435_500_00435",
            "SEGMENTATION": "폴리곤",
            "COORDINATE": [
                [
                    2358.775599997491,
                    1209.931199997663
                ],
                [
                    2373.352399997413,
                    1233.301599994302
                ],
                [
                    2400.0,
                    1218.341199994087
                ],
                [
                    2400.0,
                    1305.065999999642
                ],
                [
                    2387.340399999171,
                    1341.995200000703
                ],
                [
                    2384.367599997669,
                    1498.627999998629
                ],
                [
                    2383.709999997169,
                    1525.461599998176
                ],
                [
                    2382.52519999817,
                    1600.0
                ],
                [
                    2293.823999997228,
                    1600.0
                ],
                [
                    2293.949999999255,
                    1514.232000000775
                ],
                [
                    2294.670800000429,
                    1390.783999994397
                ],
                [
                    2280.034800000489,
                    1383.841600000858
                ],
                [
                    2161.026399999857,
                    1512.646399997175
                ],
                [
                    2083.530400000513,
                    1600.0
                ],
                [
                    2039.490399997681,
                    1600.0
                ],
                [
                    2127.951999999583,
                    1503.916799999774
                ],
                [
                    2266.913599997759,
                    1347.672799997032
                ],
                [
                    2254.131599999964,
                    1334.638399995863
                ],
                [
                    2276.533199999481,
                    1334.638399995863
                ],
                [
                    2277.462799999863,
                    1335.586399994791
                ],
                [
                    2278.075199998915,
                    1334.638399995863
                ],
                [
                    2326.911199998111,
                    1334.638399995863
                ],
                [
                    2326.911199998111,
                    1214.638399995863
                ],
                [
                    2359.55719999969,
                    1150.104399994016
                ],
                [
                    2359.053999997675,
                    1171.315999999642
                ],
                [
                    2358.775599997491,
                    1209.931199997663
                ]
            ]
        },
        {
            "ID": "4",
            "IMAGE_ID": "Oncheon_435_500_00435",
            "CATEGORY_ID": "Oncheon_435_500_00435",
            "SEGMENTATION": "폴리곤",
            "COORDINATE": [
                [
                    697.6343999989331,
                    1600.0
                ],
                [
                    694.4575999975204,
                    1600.0
                ],
                [
                    694.0663999989629,
                    1598.215999998152
                ],
                [
                    697.6343999989331,
                    1600.0
                ]
            ]
        },
        {
            "ID": "4",
            "IMAGE_ID": "Oncheon_435_500_00435",
            "CATEGORY_ID": "Oncheon_435_500_00435",
            "SEGMENTATION": "폴리곤",
            "COORDINATE": [
                [
                    666.666400000453,
                    1600.0
                ],
                [
                    406.9111999981105,
                    1600.0
                ],
                [
                    406.9111999981105,
                    1574.638399995863
                ],
                [
                    526.9111999981105,
                    1574.638399995863
                ],
                [
                    646.9111999981105,
                    1574.638399995863
                ],
                [
                    662.9560000002384,
                    1582.660799995065
                ],
                [
                    666.666400000453,
                    1600.0
                ]
            ]
        },
        {
            "ID": "4",
            "IMAGE_ID": "Oncheon_435_500_00435",
            "CATEGORY_ID": "Oncheon_435_500_00435",
            "SEGMENTATION": "폴리곤",
            "COORDINATE": [
                [
                    2293.823999997228,
                    1600.0
                ],
                [
                    2083.530400000513,
                    1600.0
                ],
                [
                    2161.026399999857,
                    1512.646399997175
                ],
                [
                    2280.034800000489,
                    1383.841600000858
                ],
                [
                    2294.670800000429,
                    1390.783999994397
                ],
                [
                    2293.949999999255,
                    1514.232000000775
                ],
                [
                    2293.823999997228,
                    1600.0
                ]
            ]
        },
        {
            "ID": "4",
            "IMAGE_ID": "Oncheon_435_500_00435",
            "CATEGORY_ID": "Oncheon_435_500_00435",
            "SEGMENTATION": "폴리곤",
            "COORDINATE": [
                [
                    2039.490399997681,
                    1600.0
                ],
                [
                    1966.911199998111,
                    1600.0
                ],
                [
                    1966.911199998111,
                    1454.638399995863
                ],
                [
                    2086.911199998111,
                    1454.638399995863
                ],
                [
                    2086.911199998111,
                    1334.638399995863
                ],
                [
                    2206.911199998111,
                    1334.638399995863
                ],
                [
                    2254.131599999964,
                    1334.638399995863
                ],
                [
                    2266.913599997759,
                    1347.672799997032
                ],
                [
                    2127.951999999583,
                    1503.916799999774
                ],
                [
                    2039.490399997681,
                    1600.0
                ]
            ]
        },
        {
            "ID": "4",
            "IMAGE_ID": "Oncheon_435_500_00435",
            "CATEGORY_ID": "Oncheon_435_500_00435",
            "SEGMENTATION": "폴리곤",
            "COORDINATE": [
                [
                    2278.075199998915,
                    1334.638399995863
                ],
                [
                    2277.462799999863,
                    1335.586399994791
                ],
                [
                    2276.533199999481,
                    1334.638399995863
                ],
                [
                    2278.075199998915,
                    1334.638399995863
                ]
            ]
        },
        {
            "ID": "4",
            "IMAGE_ID": "Oncheon_435_500_00435",
            "CATEGORY_ID": "Oncheon_435_500_00435",
            "SEGMENTATION": "폴리곤",
            "COORDINATE": [
                [
                    2400.0,
                    1600.0
                ],
                [
                    2382.52519999817,
                    1600.0
                ],
                [
                    2383.709999997169,
                    1525.461599998176
                ],
                [
                    2384.367599997669,
                    1498.627999998629
                ],
                [
                    2387.340399999171,
                    1341.995200000703
                ],
                [
                    2400.0,
                    1305.065999999642
                ],
                [
                    2400.0,
                    1600.0
                ]
            ]
        },
        {
            "ID": "4",
            "IMAGE_ID": "Oncheon_435_500_00435",
            "CATEGORY_ID": "Oncheon_435_500_00435",
            "SEGMENTATION": "폴리곤",
            "COORDINATE": [
                [
                    2400.0,
                    1218.341199994087
                ],
                [
                    2373.352399997413,
                    1233.301599994302
                ],
                [
                    2358.775599997491,
                    1209.931199997663
                ],
                [
                    2359.053999997675,
                    1171.315999999642
                ],
                [
                    2359.55719999969,
                    1150.104399994016
                ],
                [
                    2400.0,
                    1070.15719999373
                ],
                [
                    2400.0,
                    1218.341199994087
                ]
            ]
        },
        {
            "ID": "6",
            "IMAGE_ID": "Oncheon_435_500_00435",
            "CATEGORY_ID": "Oncheon_435_500_00435",
            "SEGMENTATION": "폴리곤",
            "COORDINATE": [
                [
                    406.9111999981105,
                    1600.0
                ],
                [
                    286.9111999981105,
                    1600.0
                ],
                [
                    286.9111999981105,
                    1574.638399995863
                ],
                [
                    406.9111999981105,
                    1574.638399995863
                ],
                [
                    406.9111999981105,
                    1600.0
                ]
            ]
        },
        {
            "ID": "6",
            "IMAGE_ID": "Oncheon_435_500_00435",
            "CATEGORY_ID": "Oncheon_435_500_00435",
            "SEGMENTATION": "폴리곤",
            "COORDINATE": [
                [
                    646.9111999981105,
                    1574.638399995863
                ],
                [
                    526.9111999981105,
                    1574.638399995863
                ],
                [
                    526.9111999981105,
                    1454.638399995863
                ],
                [
                    646.9111999981105,
                    1454.638399995863
                ],
                [
                    646.9111999981105,
                    1574.638399995863
                ]
            ]
        },
        {
            "ID": "6",
            "IMAGE_ID": "Oncheon_435_500_00435",
            "CATEGORY_ID": "Oncheon_435_500_00435",
            "SEGMENTATION": "폴리곤",
            "COORDINATE": [
                [
                    2086.911199998111,
                    1454.638399995863
                ],
                [
                    1966.911199998111,
                    1454.638399995863
                ],
                [
                    1966.911199998111,
                    1334.638399995863
                ],
                [
                    2086.911199998111,
                    1334.638399995863
                ],
                [
                    2086.911199998111,
                    1454.638399995863
                ]
            ]
        },
        {
            "ID": "6",
            "IMAGE_ID": "Oncheon_435_500_00435",
            "CATEGORY_ID": "Oncheon_435_500_00435",
            "SEGMENTATION": "폴리곤",
            "COORDINATE": [
                [
                    2254.131599999964,
                    1334.638399995863
                ],
                [
                    2206.911199998111,
                    1334.638399995863
                ],
                [
                    2206.911199998111,
                    1214.638399995863
                ],
                [
                    2326.911199998111,
                    1214.638399995863
                ],
                [
                    2326.911199998111,
                    1334.638399995863
                ],
                [
                    2278.075199998915,
                    1334.638399995863
                ],
                [
                    2276.533199999481,
                    1334.638399995863
                ],
                [
                    2254.131599999964,
                    1334.638399995863
                ]
            ]
        },
        {
            "ID": "7",
            "IMAGE_ID": "Oncheon_435_500_00435",
            "CATEGORY_ID": "Oncheon_435_500_00435",
            "SEGMENTATION": "폴리곤",
            "COORDINATE": [
                [
                    286.9111999981105,
                    1600.0
                ],
                [
                    0.0,
                    1600.0
                ],
                [
                    0.0,
                    1590.284800000489
                ],
                [
                    472.66079999879,
                    1376.063999995589
                ],
                [
                    526.9111999981105,
                    1454.638399995863
                ],
                [
                    526.9111999981105,
                    1574.638399995863
                ],
                [
                    406.9111999981105,
                    1574.638399995863
                ],
                [
                    286.9111999981105,
                    1574.638399995863
                ],
                [
                    286.9111999981105,
                    1600.0
                ]
            ]
        },
        {
            "ID": "7",
            "IMAGE_ID": "Oncheon_435_500_00435",
            "CATEGORY_ID": "Oncheon_435_500_00435",
            "SEGMENTATION": "폴리곤",
            "COORDINATE": [
                [
                    1966.911199998111,
                    1334.638399995863
                ],
                [
                    1966.911199998111,
                    1454.638399995863
                ],
                [
                    1966.911199998111,
                    1600.0
                ],
                [
                    697.6343999989331,
                    1600.0
                ],
                [
                    694.0663999989629,
                    1598.215999998152
                ],
                [
                    662.9560000002384,
                    1582.660799995065
                ],
                [
                    646.9111999981105,
                    1574.638399995863
                ],
                [
                    646.9111999981105,
                    1454.638399995863
                ],
                [
                    721.7791999988258,
                    1170.868799999356
                ],
                [
                    1598.737199999392,
                    1344.159999996424
                ],
                [
                    2017.008799999952,
                    1024.73599999398
                ],
                [
                    2400.0,
                    877.0223999992013
                ],
                [
                    2400.0,
                    1070.15719999373
                ],
                [
                    2359.55719999969,
                    1150.104399994016
                ],
                [
                    2326.911199998111,
                    1214.638399995863
                ],
                [
                    2206.911199998111,
                    1214.638399995863
                ],
                [
                    2206.911199998111,
                    1334.638399995863
                ],
                [
                    2086.911199998111,
                    1334.638399995863
                ],
                [
                    1966.911199998111,
                    1334.638399995863
                ]
            ]
        },
        {
            "ID": "7",
            "IMAGE_ID": "Oncheon_435_500_00435",
            "CATEGORY_ID": "Oncheon_435_500_00435",
            "SEGMENTATION": "폴리곤",
            "COORDINATE": [
                [
                    237.8975999988616,
                    303.6519999951124
                ],
                [
                    286.9111999981105,
                    614.6383999958634
                ],
                [
                    0.0,
                    541.0079999938607
                ],
                [
                    0.0,
                    232.3655999973416
                ],
                [
                    237.8975999988616,
                    303.6519999951124
                ]
            ]
        },
        {
            "ID": "8",
            "IMAGE_ID": "Oncheon_435_500_00435",
            "CATEGORY_ID": "Oncheon_435_500_00435",
            "SEGMENTATION": "폴리곤",
            "COORDINATE": [
                [
                    2400.0,
                    478.9263999983668
                ],
                [
                    2400.0,
                    719.8719999939203
                ],
                [
                    2379.125599998981,
                    552.0307999998331
                ],
                [
                    2400.0,
                    478.9263999983668
                ]
            ]
        },
        {
            "ID": "8",
            "IMAGE_ID": "Oncheon_435_500_00435",
            "CATEGORY_ID": "Oncheon_435_500_00435",
            "SEGMENTATION": "폴리곤",
            "COORDINATE": [
                [
                    886.9111999981105,
                    254.6383999958634
                ],
                [
                    961.0615999996662,
                    847.445999994874
                ],
                [
                    1203.705599997193,
                    1028.002799995244
                ],
                [
                    2400.0,
                    756.2631999999285
                ],
                [
                    2400.0,
                    877.0223999992013
                ],
                [
                    2017.008799999952,
                    1024.73599999398
                ],
                [
                    1598.737199999392,
                    1344.159999996424
                ],
                [
                    721.7791999988258,
                    1170.868799999356
                ],
                [
                    646.9111999981105,
                    1454.638399995863
                ],
                [
                    526.9111999981105,
                    1454.638399995863
                ],
                [
                    472.66079999879,
                    1376.063999995589
                ],
                [
                    0.0,
                    1590.284800000489
                ],
                [
                    0.0,
                    1037.97839999944
                ],
                [
                    217.8000000007451,
                    974.0671999976039
                ],
                [
                    0.0,
                    839.7232000008225
                ],
                [
                    0.0,
                    541.0079999938607
                ],
                [
                    286.9111999981105,
                    614.6383999958634
                ],
                [
                    237.8975999988616,
                    303.6519999951124
                ],
                [
                    0.0,
                    232.3655999973416
                ],
                [
                    0.0,
                    0.0
                ],
                [
                    886.9111999981105,
                    0.0
                ],
                [
                    886.9111999981105,
                    14.63839999586344
                ],
                [
                    719.4868000000715,
                    134.6383999958634
                ],
                [
                    886.9111999981105,
                    254.6383999958634
                ]
            ]
        },
        {
            "ID": "8",
            "IMAGE_ID": "Oncheon_435_500_00435",
            "CATEGORY_ID": "Oncheon_435_500_00435",
            "SEGMENTATION": "폴리곤",
            "COORDINATE": [
                [
                    1846.911199998111,
                    134.6383999958634
                ],
                [
                    1405.824799999595,
                    304.1796000003815
                ],
                [
                    1434.374399997294,
                    74.63839999586344
                ],
                [
                    1425.091199997813,
                    0.0
                ],
                [
                    1846.911199998111,
                    0.0
                ],
                [
                    1846.911199998111,
                    14.63839999586344
                ],
                [
                    1846.911199998111,
                    134.6383999958634
                ]
            ]
        },
        {
            "ID": "9",
            "IMAGE_ID": "Oncheon_435_500_00435",
            "CATEGORY_ID": "Oncheon_435_500_00435",
            "SEGMENTATION": "폴리곤",
            "COORDINATE": [
                [
                    217.8000000007451,
                    974.0671999976039
                ],
                [
                    0.0,
                    1037.97839999944
                ],
                [
                    0.0,
                    839.7232000008225
                ],
                [
                    217.8000000007451,
                    974.0671999976039
                ]
            ]
        },
        {
            "ID": "9",
            "IMAGE_ID": "Oncheon_435_500_00435",
            "CATEGORY_ID": "Oncheon_435_500_00435",
            "SEGMENTATION": "폴리곤",
            "COORDINATE": [
                [
                    886.9111999981105,
                    254.6383999958634
                ],
                [
                    719.4868000000715,
                    134.6383999958634
                ],
                [
                    886.9111999981105,
                    14.63839999586344
                ],
                [
                    886.9111999981105,
                    254.6383999958634
                ]
            ]
        },
        {
            "ID": "9",
            "IMAGE_ID": "Oncheon_435_500_00435",
            "CATEGORY_ID": "Oncheon_435_500_00435",
            "SEGMENTATION": "폴리곤",
            "COORDINATE": [
                [
                    1966.911199998111,
                    14.63839999586344
                ],
                [
                    1846.911199998111,
                    14.63839999586344
                ],
                [
                    1846.911199998111,
                    0.0
                ],
                [
                    1966.911199998111,
                    0.0
                ],
                [
                    1966.911199998111,
                    14.63839999586344
                ]
            ]
        },
        {
            "ID": "9",
            "IMAGE_ID": "Oncheon_435_500_00435",
            "CATEGORY_ID": "Oncheon_435_500_00435",
            "SEGMENTATION": "폴리곤",
            "COORDINATE": [
                [
                    886.9111999981105,
                    254.6383999958634
                ],
                [
                    1126.911199998111,
                    254.6383999958634
                ],
                [
                    1126.911199998111,
                    0.0
                ],
                [
                    1425.091199997813,
                    0.0
                ],
                [
                    1434.374399997294,
                    74.63839999586344
                ],
                [
                    1405.824799999595,
                    304.1796000003815
                ],
                [
                    1846.911199998111,
                    134.6383999958634
                ],
                [
                    1805.514799997211,
                    333.2419999986887
                ],
                [
                    1588.930399999022,
                    612.6463999971747
                ],
                [
                    1944.594399999827,
                    772.445999994874
                ],
                [
                    2335.905999999493,
                    0.0
                ],
                [
                    2400.0,
                    0.0
                ],
                [
                    2400.0,
                    478.9263999983668
                ],
                [
                    2379.125599998981,
                    552.0307999998331
                ],
                [
                    2400.0,
                    719.8719999939203
                ],
                [
                    2400.0,
                    756.2631999999285
                ],
                [
                    1203.705599997193,
                    1028.002799995244
                ],
                [
                    961.0615999996662,
                    847.445999994874
                ],
                [
                    886.9111999981105,
                    254.6383999958634
                ]
            ]
        },
        {
            "ID": "10",
            "IMAGE_ID": "Oncheon_435_500_00435",
            "CATEGORY_ID": "Oncheon_435_500_00435",
            "SEGMENTATION": "폴리곤",
            "COORDINATE": [
                [
                    1126.911199998111,
                    254.6383999958634
                ],
                [
                    886.9111999981105,
                    254.6383999958634
                ],
                [
                    886.9111999981105,
                    14.63839999586344
                ],
                [
                    886.9111999981105,
                    0.0
                ],
                [
                    1126.911199998111,
                    0.0
                ],
                [
                    1126.911199998111,
                    254.6383999958634
                ]
            ]
        },
        {
            "ID": "10",
            "IMAGE_ID": "Oncheon_435_500_00435",
            "CATEGORY_ID": "Oncheon_435_500_00435",
            "SEGMENTATION": "폴리곤",
            "COORDINATE": [
                [
                    2335.905999999493,
                    0.0
                ],
                [
                    1944.594399999827,
                    772.445999994874
                ],
                [
                    1588.930399999022,
                    612.6463999971747
                ],
                [
                    1805.514799997211,
                    333.2419999986887
                ],
                [
                    1846.911199998111,
                    134.6383999958634
                ],
                [
                    1846.911199998111,
                    14.63839999586344
                ],
                [
                    1966.911199998111,
                    14.63839999586344
                ],
                [
                    1966.911199998111,
                    0.0
                ],
                [
                    2335.905999999493,
                    0.0
                ]
            ]
        }
    ]
}